{"config": {"view": {"continuousWidth": 400, "continuousHeight": 300}}, "layer": [{"mark": {"type": "circle", "size": 100}, "encoding": {"color": {"type": "nominal", "field": "Measurements", "sort": null}, "opacity": {"condition": {"value": 1, "selection": "selector001"}, "value": 0}, "tooltip": [{"type": "nominal", "field": "Measurements"}, {"type": "quantitative", "field": "Freq"}, {"type": "quantitative", "field": "dB"}], "x": {"type": "quantitative", "field": "Freq", "scale": {"domain": [20, 20000], "type": "log"}}, "y": {"type": "quantitative", "field": "dB", "scale": {"zero": false}}}, "selection": {"selector396": {"type": "multi", "fields": ["Measurements"], "bind": "legend"}, "selector397": {"type": "interval", "bind": "scales"}, "selector001": {"type": "single", "nearest": true, "on": "mouseover", "fields": ["Freq"], "empty": "none"}}, "transform": [{"calculate": "format(datum.Freq, \".0f\")", "as": "Freq"}, {"calculate": "format(datum.dB, \".1f\")", "as": "dB"}]}, {"mark": "line", "encoding": {"color": {"type": "nominal", "field": "Measurements", "sort": null}, "opacity": {"condition": {"value": 1, "selection": "selector396"}, "value": 0.2}, "x": {"type": "quantitative", "field": "Freq", "scale": {"domain": [20, 20000], "type": "log"}}, "y": {"type": "quantitative", "field": "dB", "scale": {"zero": false}}}, "height": 600, "width": 1200}], "data": {"name": "data-47ce81a46077d3484810bddadd261b89"}, "$schema": "https://vega.github.io/schema/vega-lite/v4.0.2.json", "datasets": {"data-47ce81a46077d3484810bddadd261b89": [{"Freq": 20.5078, "Measurements": "Floor Reflection", "dB": 51.7996}, {"Freq": 21.2402, "Measurements": "Floor Reflection", "dB": 51.3592}, {"Freq": 21.9727, "Measurements": "Floor Reflection", "dB": 53.5704}, {"Freq": 22.7051, "Measurements": "Floor Reflection", "dB": 56.0567}, {"Freq": 23.4375, "Measurements": "Floor Reflection", "dB": 60.0396}, {"Freq": 24.1699, "Measurements": "Floor Reflection", "dB": 61.1771}, {"Freq": 25.6348, "Measurements": "Floor Reflection", "dB": 65.1245}, {"Freq": 26.3672, "Measurements": "Floor Reflection", "dB": 66.708}, {"Freq": 27.0996, "Measurements": "Floor Reflection", "dB": 68.6799}, {"Freq": 27.832, "Measurements": "Floor Reflection", "dB": 70.3685}, {"Freq": 29.2969, "Measurements": "Floor Reflection", "dB": 73.6881}, {"Freq": 30.0293, "Measurements": "Floor Reflection", "dB": 75.2524}, {"Freq": 31.4941, "Measurements": "Floor Reflection", "dB": 78.2116}, {"Freq": 32.2266, "Measurements": "Floor Reflection", "dB": 79.6261}, {"Freq": 33.6914, "Measurements": "Floor Reflection", "dB": 82.1486}, {"Freq": 34.4238, "Measurements": "Floor Reflection", "dB": 83.3132}, {"Freq": 35.8887, "Measurements": "Floor Reflection", "dB": 85.4562}, {"Freq": 37.3535, "Measurements": "Floor Reflection", "dB": 87.2864}, {"Freq": 38.8184, "Measurements": "Floor Reflection", "dB": 88.7442}, {"Freq": 39.5508, "Measurements": "Floor Reflection", "dB": 89.309}, {"Freq": 41.0156, "Measurements": "Floor Reflection", "dB": 90.3515}, {"Freq": 42.4805, "Measurements": "Floor Reflection", "dB": 91.165}, {"Freq": 43.9453, "Measurements": "Floor Reflection", "dB": 91.7468}, {"Freq": 45.4102, "Measurements": "Floor Reflection", "dB": 92.1371}, {"Freq": 47.6074, "Measurements": "Floor Reflection", "dB": 92.5327}, {"Freq": 49.0723, "Measurements": "Floor Reflection", "dB": 92.7097}, {"Freq": 50.5371, "Measurements": "Floor Reflection", "dB": 92.8386}, {"Freq": 52.7344, "Measurements": "Floor Reflection", "dB": 92.9856}, {"Freq": 54.1992, "Measurements": "Floor Reflection", "dB": 93.0436}, {"Freq": 56.3965, "Measurements": "Floor Reflection", "dB": 93.0883}, {"Freq": 58.5938, "Measurements": "Floor Reflection", "dB": 93.1485}, {"Freq": 60.0586, "Measurements": "Floor Reflection", "dB": 93.197}, {"Freq": 62.2559, "Measurements": "Floor Reflection", "dB": 93.2231}, {"Freq": 64.4531, "Measurements": "Floor Reflection", "dB": 93.2619}, {"Freq": 66.6504, "Measurements": "Floor Reflection", "dB": 93.2941}, {"Freq": 69.5801, "Measurements": "Floor Reflection", "dB": 93.3586}, {"Freq": 71.7773, "Measurements": "Floor Reflection", "dB": 93.3724}, {"Freq": 73.9746, "Measurements": "Floor Reflection", "dB": 93.3923}, {"Freq": 76.9043, "Measurements": "Floor Reflection", "dB": 93.4099}, {"Freq": 79.834, "Measurements": "Floor Reflection", "dB": 93.5008}, {"Freq": 82.7637, "Measurements": "Floor Reflection", "dB": 93.646}, {"Freq": 85.6934, "Measurements": "Floor Reflection", "dB": 93.5766}, {"Freq": 88.623, "Measurements": "Floor Reflection", "dB": 93.4834}, {"Freq": 91.5527, "Measurements": "Floor Reflection", "dB": 93.4843}, {"Freq": 94.4824, "Measurements": "Floor Reflection", "dB": 93.6166}, {"Freq": 98.1445, "Measurements": "Floor Reflection", "dB": 93.7138}, {"Freq": 101.807, "Measurements": "Floor Reflection", "dB": 93.6587}, {"Freq": 105.469, "Measurements": "Floor Reflection", "dB": 93.6533}, {"Freq": 109.131, "Measurements": "Floor Reflection", "dB": 93.7563}, {"Freq": 112.793, "Measurements": "Floor Reflection", "dB": 93.6088}, {"Freq": 116.455, "Measurements": "Floor Reflection", "dB": 93.588}, {"Freq": 120.85, "Measurements": "Floor Reflection", "dB": 93.8068}, {"Freq": 125.244, "Measurements": "Floor Reflection", "dB": 93.7551}, {"Freq": 129.639, "Measurements": "Floor Reflection", "dB": 93.6342}, {"Freq": 134.033, "Measurements": "Floor Reflection", "dB": 93.5681}, {"Freq": 138.428, "Measurements": "Floor Reflection", "dB": 93.4364}, {"Freq": 143.555, "Measurements": "Floor Reflection", "dB": 93.3815}, {"Freq": 148.682, "Measurements": "Floor Reflection", "dB": 93.3821}, {"Freq": 153.809, "Measurements": "Floor Reflection", "dB": 93.3026}, {"Freq": 159.668, "Measurements": "Floor Reflection", "dB": 93.1678}, {"Freq": 164.795, "Measurements": "Floor Reflection", "dB": 92.7811}, {"Freq": 170.654, "Measurements": "Floor Reflection", "dB": 92.9552}, {"Freq": 176.514, "Measurements": "Floor Reflection", "dB": 93.2536}, {"Freq": 183.105, "Measurements": "Floor Reflection", "dB": 93.5501}, {"Freq": 189.697, "Measurements": "Floor Reflection", "dB": 93.8141}, {"Freq": 196.289, "Measurements": "Floor Reflection", "dB": 93.7708}, {"Freq": 202.881, "Measurements": "Floor Reflection", "dB": 93.7923}, {"Freq": 210.205, "Measurements": "Floor Reflection", "dB": 93.7418}, {"Freq": 217.529, "Measurements": "Floor Reflection", "dB": 93.6226}, {"Freq": 225.586, "Measurements": "Floor Reflection", "dB": 93.763}, {"Freq": 232.91, "Measurements": "Floor Reflection", "dB": 93.8855}, {"Freq": 241.699, "Measurements": "Floor Reflection", "dB": 93.8857}, {"Freq": 249.756, "Measurements": "Floor Reflection", "dB": 94.083}, {"Freq": 258.545, "Measurements": "Floor Reflection", "dB": 93.9921}, {"Freq": 268.066, "Measurements": "Floor Reflection", "dB": 93.6091}, {"Freq": 277.588, "Measurements": "Floor Reflection", "dB": 93.1581}, {"Freq": 287.109, "Measurements": "Floor Reflection", "dB": 92.6275}, {"Freq": 297.363, "Measurements": "Floor Reflection", "dB": 92.6253}, {"Freq": 307.617, "Measurements": "Floor Reflection", "dB": 91.7925}, {"Freq": 318.604, "Measurements": "Floor Reflection", "dB": 91.3358}, {"Freq": 329.59, "Measurements": "Floor Reflection", "dB": 91.8087}, {"Freq": 341.309, "Measurements": "Floor Reflection", "dB": 91.3712}, {"Freq": 353.76, "Measurements": "Floor Reflection", "dB": 91.6741}, {"Freq": 366.211, "Measurements": "Floor Reflection", "dB": 91.9171}, {"Freq": 378.662, "Measurements": "Floor Reflection", "dB": 92.4723}, {"Freq": 392.578, "Measurements": "Floor Reflection", "dB": 92.5314}, {"Freq": 405.762, "Measurements": "Floor Reflection", "dB": 92.5014}, {"Freq": 420.41, "Measurements": "Floor Reflection", "dB": 93.1788}, {"Freq": 435.059, "Measurements": "Floor Reflection", "dB": 92.7174}, {"Freq": 450.439, "Measurements": "Floor Reflection", "dB": 93.0445}, {"Freq": 466.553, "Measurements": "Floor Reflection", "dB": 93.2969}, {"Freq": 482.666, "Measurements": "Floor Reflection", "dB": 93.1393}, {"Freq": 500.244, "Measurements": "Floor Reflection", "dB": 93.2837}, {"Freq": 517.822, "Measurements": "Floor Reflection", "dB": 93.2264}, {"Freq": 536.133, "Measurements": "Floor Reflection", "dB": 93.4511}, {"Freq": 554.443, "Measurements": "Floor Reflection", "dB": 93.1944}, {"Freq": 574.219, "Measurements": "Floor Reflection", "dB": 93.8219}, {"Freq": 594.727, "Measurements": "Floor Reflection", "dB": 93.5114}, {"Freq": 615.234, "Measurements": "Floor Reflection", "dB": 93.4211}, {"Freq": 637.207, "Measurements": "Floor Reflection", "dB": 93.8422}, {"Freq": 659.912, "Measurements": "Floor Reflection", "dB": 93.778}, {"Freq": 683.35, "Measurements": "Floor Reflection", "dB": 94.0986}, {"Freq": 706.787, "Measurements": "Floor Reflection", "dB": 94.0548}, {"Freq": 731.689, "Measurements": "Floor Reflection", "dB": 94.1974}, {"Freq": 758.057, "Measurements": "Floor Reflection", "dB": 93.9432}, {"Freq": 784.424, "Measurements": "Floor Reflection", "dB": 93.4446}, {"Freq": 812.256, "Measurements": "Floor Reflection", "dB": 92.881}, {"Freq": 840.82, "Measurements": "Floor Reflection", "dB": 93.4064}, {"Freq": 870.85, "Measurements": "Floor Reflection", "dB": 93.9476}, {"Freq": 901.611, "Measurements": "Floor Reflection", "dB": 93.7725}, {"Freq": 933.105, "Measurements": "Floor Reflection", "dB": 94.319}, {"Freq": 966.064, "Measurements": "Floor Reflection", "dB": 94.4369}, {"Freq": 999.756, "Measurements": "Floor Reflection", "dB": 94.0722}, {"Freq": 1034.91, "Measurements": "Floor Reflection", "dB": 93.8547}, {"Freq": 1071.53, "Measurements": "Floor Reflection", "dB": 93.6862}, {"Freq": 1109.62, "Measurements": "Floor Reflection", "dB": 93.5936}, {"Freq": 1148.44, "Measurements": "Floor Reflection", "dB": 93.4512}, {"Freq": 1189.45, "Measurements": "Floor Reflection", "dB": 93.0257}, {"Freq": 1231.2, "Measurements": "Floor Reflection", "dB": 92.8727}, {"Freq": 1274.41, "Measurements": "Floor Reflection", "dB": 92.6401}, {"Freq": 1319.82, "Measurements": "Floor Reflection", "dB": 92.4593}, {"Freq": 1365.97, "Measurements": "Floor Reflection", "dB": 91.9903}, {"Freq": 1414.31, "Measurements": "Floor Reflection", "dB": 91.7131}, {"Freq": 1464.11, "Measurements": "Floor Reflection", "dB": 91.5599}, {"Freq": 1515.38, "Measurements": "Floor Reflection", "dB": 91.314}, {"Freq": 1568.85, "Measurements": "Floor Reflection", "dB": 90.8964}, {"Freq": 1624.51, "Measurements": "Floor Reflection", "dB": 90.2667}, {"Freq": 1681.64, "Measurements": "Floor Reflection", "dB": 90.3631}, {"Freq": 1740.97, "Measurements": "Floor Reflection", "dB": 89.8757}, {"Freq": 1802.49, "Measurements": "Floor Reflection", "dB": 89.2455}, {"Freq": 1866.21, "Measurements": "Floor Reflection", "dB": 89.7012}, {"Freq": 1932.13, "Measurements": "Floor Reflection", "dB": 89.1751}, {"Freq": 2000.24, "Measurements": "Floor Reflection", "dB": 88.4207}, {"Freq": 2070.56, "Measurements": "Floor Reflection", "dB": 89.2199}, {"Freq": 2143.8, "Measurements": "Floor Reflection", "dB": 90.1447}, {"Freq": 2219.24, "Measurements": "Floor Reflection", "dB": 90.4829}, {"Freq": 2297.61, "Measurements": "Floor Reflection", "dB": 90.4666}, {"Freq": 2378.17, "Measurements": "Floor Reflection", "dB": 90.7419}, {"Freq": 2462.4, "Measurements": "Floor Reflection", "dB": 90.9658}, {"Freq": 2548.83, "Measurements": "Floor Reflection", "dB": 90.665}, {"Freq": 2638.92, "Measurements": "Floor Reflection", "dB": 90.1384}, {"Freq": 2731.93, "Measurements": "Floor Reflection", "dB": 89.7833}, {"Freq": 2828.61, "Measurements": "Floor Reflection", "dB": 89.2863}, {"Freq": 2928.22, "Measurements": "Floor Reflection", "dB": 89.1018}, {"Freq": 3031.49, "Measurements": "Floor Reflection", "dB": 89.0713}, {"Freq": 3138.43, "Measurements": "Floor Reflection", "dB": 89.0299}, {"Freq": 3249.02, "Measurements": "Floor Reflection", "dB": 89.1615}, {"Freq": 3363.28, "Measurements": "Floor Reflection", "dB": 89.1418}, {"Freq": 3481.93, "Measurements": "Floor Reflection", "dB": 89.158}, {"Freq": 3604.98, "Measurements": "Floor Reflection", "dB": 89.4699}, {"Freq": 3732.42, "Measurements": "Floor Reflection", "dB": 89.7159}, {"Freq": 3863.53, "Measurements": "Floor Reflection", "dB": 89.5709}, {"Freq": 3999.76, "Measurements": "Floor Reflection", "dB": 89.4342}, {"Freq": 4141.11, "Measurements": "Floor Reflection", "dB": 89.088}, {"Freq": 4286.87, "Measurements": "Floor Reflection", "dB": 89.2168}, {"Freq": 4438.48, "Measurements": "Floor Reflection", "dB": 89.3258}, {"Freq": 4594.48, "Measurements": "Floor Reflection", "dB": 89.349}, {"Freq": 4757.08, "Measurements": "Floor Reflection", "dB": 89.2308}, {"Freq": 4924.8, "Measurements": "Floor Reflection", "dB": 88.757}, {"Freq": 5098.39, "Measurements": "Floor Reflection", "dB": 87.8594}, {"Freq": 5277.83, "Measurements": "Floor Reflection", "dB": 87.615}, {"Freq": 5463.87, "Measurements": "Floor Reflection", "dB": 88.7785}, {"Freq": 5656.49, "Measurements": "Floor Reflection", "dB": 89.3889}, {"Freq": 5856.45, "Measurements": "Floor Reflection", "dB": 89.6278}, {"Freq": 6062.99, "Measurements": "Floor Reflection", "dB": 89.9114}, {"Freq": 6276.86, "Measurements": "Floor Reflection", "dB": 90.0573}, {"Freq": 6498.05, "Measurements": "Floor Reflection", "dB": 90.0876}, {"Freq": 6727.29, "Measurements": "Floor Reflection", "dB": 90.065}, {"Freq": 6964.6, "Measurements": "Floor Reflection", "dB": 90.7718}, {"Freq": 7209.96, "Measurements": "Floor Reflection", "dB": 91.1342}, {"Freq": 7464.11, "Measurements": "Floor Reflection", "dB": 91.4436}, {"Freq": 7727.78, "Measurements": "Floor Reflection", "dB": 90.4847}, {"Freq": 8000.24, "Measurements": "Floor Reflection", "dB": 89.6369}, {"Freq": 8282.23, "Measurements": "Floor Reflection", "dB": 88.5206}, {"Freq": 8574.46, "Measurements": "Floor Reflection", "dB": 87.5357}, {"Freq": 8876.22, "Measurements": "Floor Reflection", "dB": 87.5049}, {"Freq": 9189.7, "Measurements": "Floor Reflection", "dB": 87.4277}, {"Freq": 9513.43, "Measurements": "Floor Reflection", "dB": 87.2085}, {"Freq": 9848.88, "Measurements": "Floor Reflection", "dB": 87.212}, {"Freq": 10196.8, "Measurements": "Floor Reflection", "dB": 87.4513}, {"Freq": 10556.4, "Measurements": "Floor Reflection", "dB": 87.6245}, {"Freq": 10928.5, "Measurements": "Floor Reflection", "dB": 87.5964}, {"Freq": 11313.7, "Measurements": "Floor Reflection", "dB": 87.5955}, {"Freq": 11712.9, "Measurements": "Floor Reflection", "dB": 87.7061}, {"Freq": 12126.0, "Measurements": "Floor Reflection", "dB": 87.8089}, {"Freq": 12553.7, "Measurements": "Floor Reflection", "dB": 88.2923}, {"Freq": 12996.1, "Measurements": "Floor Reflection", "dB": 88.9716}, {"Freq": 13454.6, "Measurements": "Floor Reflection", "dB": 89.3819}, {"Freq": 13928.5, "Measurements": "Floor Reflection", "dB": 89.3847}, {"Freq": 14419.9, "Measurements": "Floor Reflection", "dB": 89.3872}, {"Freq": 14928.2, "Measurements": "Floor Reflection", "dB": 89.2615}, {"Freq": 15454.8, "Measurements": "Floor Reflection", "dB": 88.9971}, {"Freq": 15999.8, "Measurements": "Floor Reflection", "dB": 88.6488}, {"Freq": 16564.5, "Measurements": "Floor Reflection", "dB": 87.661}, {"Freq": 17148.2, "Measurements": "Floor Reflection", "dB": 86.0919}, {"Freq": 17753.2, "Measurements": "Floor Reflection", "dB": 84.6668}, {"Freq": 18379.4, "Measurements": "Floor Reflection", "dB": 83.8321}, {"Freq": 19027.6, "Measurements": "Floor Reflection", "dB": 82.4985}, {"Freq": 19698.5, "Measurements": "Floor Reflection", "dB": 80.8099}, {"Freq": 19999.5, "Measurements": "Floor Reflection", "dB": 80.0362}, {"Freq": 20.5078, "Measurements": "Ceiling Reflection", "dB": 50.7409}, {"Freq": 21.2402, "Measurements": "Ceiling Reflection", "dB": 48.6642}, {"Freq": 21.9727, "Measurements": "Ceiling Reflection", "dB": 51.0244}, {"Freq": 22.7051, "Measurements": "Ceiling Reflection", "dB": 52.6538}, {"Freq": 23.4375, "Measurements": "Ceiling Reflection", "dB": 57.4699}, {"Freq": 24.1699, "Measurements": "Ceiling Reflection", "dB": 58.653}, {"Freq": 25.6348, "Measurements": "Ceiling Reflection", "dB": 62.6831}, {"Freq": 26.3672, "Measurements": "Ceiling Reflection", "dB": 64.2614}, {"Freq": 27.0996, "Measurements": "Ceiling Reflection", "dB": 66.3045}, {"Freq": 27.832, "Measurements": "Ceiling Reflection", "dB": 68.0653}, {"Freq": 29.2969, "Measurements": "Ceiling Reflection", "dB": 71.5199}, {"Freq": 30.0293, "Measurements": "Ceiling Reflection", "dB": 73.1527}, {"Freq": 31.4941, "Measurements": "Ceiling Reflection", "dB": 76.2178}, {"Freq": 32.2266, "Measurements": "Ceiling Reflection", "dB": 77.6378}, {"Freq": 33.6914, "Measurements": "Ceiling Reflection", "dB": 80.2079}, {"Freq": 34.4238, "Measurements": "Ceiling Reflection", "dB": 81.4098}, {"Freq": 35.8887, "Measurements": "Ceiling Reflection", "dB": 83.6085}, {"Freq": 37.3535, "Measurements": "Ceiling Reflection", "dB": 85.4848}, {"Freq": 38.8184, "Measurements": "Ceiling Reflection", "dB": 86.9864}, {"Freq": 39.5508, "Measurements": "Ceiling Reflection", "dB": 87.5711}, {"Freq": 41.0156, "Measurements": "Ceiling Reflection", "dB": 88.6058}, {"Freq": 42.4805, "Measurements": "Ceiling Reflection", "dB": 89.4348}, {"Freq": 43.9453, "Measurements": "Ceiling Reflection", "dB": 90.0229}, {"Freq": 45.4102, "Measurements": "Ceiling Reflection", "dB": 90.428}, {"Freq": 47.6074, "Measurements": "Ceiling Reflection", "dB": 90.9194}, {"Freq": 49.0723, "Measurements": "Ceiling Reflection", "dB": 91.1079}, {"Freq": 50.5371, "Measurements": "Ceiling Reflection", "dB": 91.2307}, {"Freq": 52.7344, "Measurements": "Ceiling Reflection", "dB": 91.3951}, {"Freq": 54.1992, "Measurements": "Ceiling Reflection", "dB": 91.4678}, {"Freq": 56.3965, "Measurements": "Ceiling Reflection", "dB": 91.5328}, {"Freq": 58.5938, "Measurements": "Ceiling Reflection", "dB": 91.6083}, {"Freq": 60.0586, "Measurements": "Ceiling Reflection", "dB": 91.6573}, {"Freq": 62.2559, "Measurements": "Ceiling Reflection", "dB": 91.6689}, {"Freq": 64.4531, "Measurements": "Ceiling Reflection", "dB": 91.7014}, {"Freq": 66.6504, "Measurements": "Ceiling Reflection", "dB": 91.7163}, {"Freq": 69.5801, "Measurements": "Ceiling Reflection", "dB": 91.7609}, {"Freq": 71.7773, "Measurements": "Ceiling Reflection", "dB": 91.803}, {"Freq": 73.9746, "Measurements": "Ceiling Reflection", "dB": 91.8846}, {"Freq": 76.9043, "Measurements": "Ceiling Reflection", "dB": 91.9072}, {"Freq": 79.834, "Measurements": "Ceiling Reflection", "dB": 91.9587}, {"Freq": 82.7637, "Measurements": "Ceiling Reflection", "dB": 92.0756}, {"Freq": 85.6934, "Measurements": "Ceiling Reflection", "dB": 92.0061}, {"Freq": 88.623, "Measurements": "Ceiling Reflection", "dB": 91.9096}, {"Freq": 91.5527, "Measurements": "Ceiling Reflection", "dB": 91.8549}, {"Freq": 94.4824, "Measurements": "Ceiling Reflection", "dB": 91.8759}, {"Freq": 98.1445, "Measurements": "Ceiling Reflection", "dB": 92.0511}, {"Freq": 101.807, "Measurements": "Ceiling Reflection", "dB": 91.9899}, {"Freq": 105.469, "Measurements": "Ceiling Reflection", "dB": 91.9384}, {"Freq": 109.131, "Measurements": "Ceiling Reflection", "dB": 91.8763}, {"Freq": 112.793, "Measurements": "Ceiling Reflection", "dB": 91.7424}, {"Freq": 116.455, "Measurements": "Ceiling Reflection", "dB": 91.7193}, {"Freq": 120.85, "Measurements": "Ceiling Reflection", "dB": 91.9567}, {"Freq": 125.244, "Measurements": "Ceiling Reflection", "dB": 91.7798}, {"Freq": 129.639, "Measurements": "Ceiling Reflection", "dB": 91.6444}, {"Freq": 134.033, "Measurements": "Ceiling Reflection", "dB": 91.4647}, {"Freq": 138.428, "Measurements": "Ceiling Reflection", "dB": 91.2166}, {"Freq": 143.555, "Measurements": "Ceiling Reflection", "dB": 90.9031}, {"Freq": 148.682, "Measurements": "Ceiling Reflection", "dB": 90.7844}, {"Freq": 153.809, "Measurements": "Ceiling Reflection", "dB": 90.6327}, {"Freq": 159.668, "Measurements": "Ceiling Reflection", "dB": 90.5023}, {"Freq": 164.795, "Measurements": "Ceiling Reflection", "dB": 89.9594}, {"Freq": 170.654, "Measurements": "Ceiling Reflection", "dB": 90.0474}, {"Freq": 176.514, "Measurements": "Ceiling Reflection", "dB": 90.2141}, {"Freq": 183.105, "Measurements": "Ceiling Reflection", "dB": 90.1175}, {"Freq": 189.697, "Measurements": "Ceiling Reflection", "dB": 90.3918}, {"Freq": 196.289, "Measurements": "Ceiling Reflection", "dB": 90.377}, {"Freq": 202.881, "Measurements": "Ceiling Reflection", "dB": 90.414}, {"Freq": 210.205, "Measurements": "Ceiling Reflection", "dB": 90.3074}, {"Freq": 217.529, "Measurements": "Ceiling Reflection", "dB": 90.3588}, {"Freq": 225.586, "Measurements": "Ceiling Reflection", "dB": 90.392}, {"Freq": 232.91, "Measurements": "Ceiling Reflection", "dB": 90.7797}, {"Freq": 241.699, "Measurements": "Ceiling Reflection", "dB": 90.6021}, {"Freq": 249.756, "Measurements": "Ceiling Reflection", "dB": 91.0569}, {"Freq": 258.545, "Measurements": "Ceiling Reflection", "dB": 91.1718}, {"Freq": 268.066, "Measurements": "Ceiling Reflection", "dB": 90.5307}, {"Freq": 277.588, "Measurements": "Ceiling Reflection", "dB": 90.676}, {"Freq": 287.109, "Measurements": "Ceiling Reflection", "dB": 90.2607}, {"Freq": 297.363, "Measurements": "Ceiling Reflection", "dB": 89.9325}, {"Freq": 307.617, "Measurements": "Ceiling Reflection", "dB": 89.2354}, {"Freq": 318.604, "Measurements": "Ceiling Reflection", "dB": 89.0213}, {"Freq": 329.59, "Measurements": "Ceiling Reflection", "dB": 89.5069}, {"Freq": 341.309, "Measurements": "Ceiling Reflection", "dB": 89.0613}, {"Freq": 353.76, "Measurements": "Ceiling Reflection", "dB": 89.4212}, {"Freq": 366.211, "Measurements": "Ceiling Reflection", "dB": 89.6729}, {"Freq": 378.662, "Measurements": "Ceiling Reflection", "dB": 90.0335}, {"Freq": 392.578, "Measurements": "Ceiling Reflection", "dB": 89.9458}, {"Freq": 405.762, "Measurements": "Ceiling Reflection", "dB": 89.8582}, {"Freq": 420.41, "Measurements": "Ceiling Reflection", "dB": 90.8034}, {"Freq": 435.059, "Measurements": "Ceiling Reflection", "dB": 90.0104}, {"Freq": 450.439, "Measurements": "Ceiling Reflection", "dB": 89.8822}, {"Freq": 466.553, "Measurements": "Ceiling Reflection", "dB": 89.4142}, {"Freq": 482.666, "Measurements": "Ceiling Reflection", "dB": 89.0239}, {"Freq": 500.244, "Measurements": "Ceiling Reflection", "dB": 88.5163}, {"Freq": 517.822, "Measurements": "Ceiling Reflection", "dB": 88.4673}, {"Freq": 536.133, "Measurements": "Ceiling Reflection", "dB": 88.6476}, {"Freq": 554.443, "Measurements": "Ceiling Reflection", "dB": 87.7296}, {"Freq": 574.219, "Measurements": "Ceiling Reflection", "dB": 88.0414}, {"Freq": 594.727, "Measurements": "Ceiling Reflection", "dB": 88.5636}, {"Freq": 615.234, "Measurements": "Ceiling Reflection", "dB": 89.0946}, {"Freq": 637.207, "Measurements": "Ceiling Reflection", "dB": 88.4898}, {"Freq": 659.912, "Measurements": "Ceiling Reflection", "dB": 87.2379}, {"Freq": 683.35, "Measurements": "Ceiling Reflection", "dB": 87.7688}, {"Freq": 706.787, "Measurements": "Ceiling Reflection", "dB": 87.8541}, {"Freq": 731.689, "Measurements": "Ceiling Reflection", "dB": 87.3457}, {"Freq": 758.057, "Measurements": "Ceiling Reflection", "dB": 88.1797}, {"Freq": 784.424, "Measurements": "Ceiling Reflection", "dB": 88.6606}, {"Freq": 812.256, "Measurements": "Ceiling Reflection", "dB": 88.5048}, {"Freq": 840.82, "Measurements": "Ceiling Reflection", "dB": 85.8986}, {"Freq": 870.85, "Measurements": "Ceiling Reflection", "dB": 87.7778}, {"Freq": 901.611, "Measurements": "Ceiling Reflection", "dB": 88.9395}, {"Freq": 933.105, "Measurements": "Ceiling Reflection", "dB": 88.8911}, {"Freq": 966.064, "Measurements": "Ceiling Reflection", "dB": 90.6597}, {"Freq": 999.756, "Measurements": "Ceiling Reflection", "dB": 90.8165}, {"Freq": 1034.91, "Measurements": "Ceiling Reflection", "dB": 91.224}, {"Freq": 1071.53, "Measurements": "Ceiling Reflection", "dB": 91.0427}, {"Freq": 1109.62, "Measurements": "Ceiling Reflection", "dB": 90.4717}, {"Freq": 1148.44, "Measurements": "Ceiling Reflection", "dB": 89.8395}, {"Freq": 1189.45, "Measurements": "Ceiling Reflection", "dB": 90.6209}, {"Freq": 1231.2, "Measurements": "Ceiling Reflection", "dB": 90.2951}, {"Freq": 1274.41, "Measurements": "Ceiling Reflection", "dB": 88.8543}, {"Freq": 1319.82, "Measurements": "Ceiling Reflection", "dB": 89.294}, {"Freq": 1365.97, "Measurements": "Ceiling Reflection", "dB": 88.4449}, {"Freq": 1414.31, "Measurements": "Ceiling Reflection", "dB": 88.5522}, {"Freq": 1464.11, "Measurements": "Ceiling Reflection", "dB": 86.4604}, {"Freq": 1515.38, "Measurements": "Ceiling Reflection", "dB": 86.2575}, {"Freq": 1568.85, "Measurements": "Ceiling Reflection", "dB": 88.7765}, {"Freq": 1624.51, "Measurements": "Ceiling Reflection", "dB": 87.1961}, {"Freq": 1681.64, "Measurements": "Ceiling Reflection", "dB": 88.4189}, {"Freq": 1740.97, "Measurements": "Ceiling Reflection", "dB": 87.1921}, {"Freq": 1802.49, "Measurements": "Ceiling Reflection", "dB": 87.32}, {"Freq": 1866.21, "Measurements": "Ceiling Reflection", "dB": 86.6544}, {"Freq": 1932.13, "Measurements": "Ceiling Reflection", "dB": 87.5629}, {"Freq": 2000.24, "Measurements": "Ceiling Reflection", "dB": 86.2298}, {"Freq": 2070.56, "Measurements": "Ceiling Reflection", "dB": 85.6189}, {"Freq": 2143.8, "Measurements": "Ceiling Reflection", "dB": 86.9123}, {"Freq": 2219.24, "Measurements": "Ceiling Reflection", "dB": 87.7878}, {"Freq": 2297.61, "Measurements": "Ceiling Reflection", "dB": 87.7036}, {"Freq": 2378.17, "Measurements": "Ceiling Reflection", "dB": 87.4721}, {"Freq": 2462.4, "Measurements": "Ceiling Reflection", "dB": 87.4696}, {"Freq": 2548.83, "Measurements": "Ceiling Reflection", "dB": 86.8573}, {"Freq": 2638.92, "Measurements": "Ceiling Reflection", "dB": 87.1433}, {"Freq": 2731.93, "Measurements": "Ceiling Reflection", "dB": 86.7568}, {"Freq": 2828.61, "Measurements": "Ceiling Reflection", "dB": 86.3312}, {"Freq": 2928.22, "Measurements": "Ceiling Reflection", "dB": 85.9713}, {"Freq": 3031.49, "Measurements": "Ceiling Reflection", "dB": 85.2929}, {"Freq": 3138.43, "Measurements": "Ceiling Reflection", "dB": 85.0245}, {"Freq": 3249.02, "Measurements": "Ceiling Reflection", "dB": 84.5411}, {"Freq": 3363.28, "Measurements": "Ceiling Reflection", "dB": 84.5473}, {"Freq": 3481.93, "Measurements": "Ceiling Reflection", "dB": 84.7276}, {"Freq": 3604.98, "Measurements": "Ceiling Reflection", "dB": 84.6656}, {"Freq": 3732.42, "Measurements": "Ceiling Reflection", "dB": 84.6946}, {"Freq": 3863.53, "Measurements": "Ceiling Reflection", "dB": 85.0245}, {"Freq": 3999.76, "Measurements": "Ceiling Reflection", "dB": 85.4365}, {"Freq": 4141.11, "Measurements": "Ceiling Reflection", "dB": 85.9031}, {"Freq": 4286.87, "Measurements": "Ceiling Reflection", "dB": 86.3927}, {"Freq": 4438.48, "Measurements": "Ceiling Reflection", "dB": 86.6908}, {"Freq": 4594.48, "Measurements": "Ceiling Reflection", "dB": 87.0202}, {"Freq": 4757.08, "Measurements": "Ceiling Reflection", "dB": 87.0869}, {"Freq": 4924.8, "Measurements": "Ceiling Reflection", "dB": 86.209}, {"Freq": 5098.39, "Measurements": "Ceiling Reflection", "dB": 85.0157}, {"Freq": 5277.83, "Measurements": "Ceiling Reflection", "dB": 85.1973}, {"Freq": 5463.87, "Measurements": "Ceiling Reflection", "dB": 86.8373}, {"Freq": 5656.49, "Measurements": "Ceiling Reflection", "dB": 87.5677}, {"Freq": 5856.45, "Measurements": "Ceiling Reflection", "dB": 88.4032}, {"Freq": 6062.99, "Measurements": "Ceiling Reflection", "dB": 88.3171}, {"Freq": 6276.86, "Measurements": "Ceiling Reflection", "dB": 87.9729}, {"Freq": 6498.05, "Measurements": "Ceiling Reflection", "dB": 87.1041}, {"Freq": 6727.29, "Measurements": "Ceiling Reflection", "dB": 86.9237}, {"Freq": 6964.6, "Measurements": "Ceiling Reflection", "dB": 86.9492}, {"Freq": 7209.96, "Measurements": "Ceiling Reflection", "dB": 86.9289}, {"Freq": 7464.11, "Measurements": "Ceiling Reflection", "dB": 86.993}, {"Freq": 7727.78, "Measurements": "Ceiling Reflection", "dB": 86.2665}, {"Freq": 8000.24, "Measurements": "Ceiling Reflection", "dB": 85.9402}, {"Freq": 8282.23, "Measurements": "Ceiling Reflection", "dB": 85.82}, {"Freq": 8574.46, "Measurements": "Ceiling Reflection", "dB": 85.358}, {"Freq": 8876.22, "Measurements": "Ceiling Reflection", "dB": 85.0299}, {"Freq": 9189.7, "Measurements": "Ceiling Reflection", "dB": 84.389}, {"Freq": 9513.43, "Measurements": "Ceiling Reflection", "dB": 84.0704}, {"Freq": 9848.88, "Measurements": "Ceiling Reflection", "dB": 84.7612}, {"Freq": 10196.8, "Measurements": "Ceiling Reflection", "dB": 86.0404}, {"Freq": 10556.4, "Measurements": "Ceiling Reflection", "dB": 86.6579}, {"Freq": 10928.5, "Measurements": "Ceiling Reflection", "dB": 86.021}, {"Freq": 11313.7, "Measurements": "Ceiling Reflection", "dB": 84.7901}, {"Freq": 11712.9, "Measurements": "Ceiling Reflection", "dB": 83.867}, {"Freq": 12126.0, "Measurements": "Ceiling Reflection", "dB": 83.2453}, {"Freq": 12553.7, "Measurements": "Ceiling Reflection", "dB": 83.1972}, {"Freq": 12996.1, "Measurements": "Ceiling Reflection", "dB": 82.8365}, {"Freq": 13454.6, "Measurements": "Ceiling Reflection", "dB": 82.3613}, {"Freq": 13928.5, "Measurements": "Ceiling Reflection", "dB": 81.6373}, {"Freq": 14419.9, "Measurements": "Ceiling Reflection", "dB": 81.4244}, {"Freq": 14928.2, "Measurements": "Ceiling Reflection", "dB": 80.8829}, {"Freq": 15454.8, "Measurements": "Ceiling Reflection", "dB": 79.9152}, {"Freq": 15999.8, "Measurements": "Ceiling Reflection", "dB": 78.7841}, {"Freq": 16564.5, "Measurements": "Ceiling Reflection", "dB": 77.0546}, {"Freq": 17148.2, "Measurements": "Ceiling Reflection", "dB": 74.8588}, {"Freq": 17753.2, "Measurements": "Ceiling Reflection", "dB": 72.5675}, {"Freq": 18379.4, "Measurements": "Ceiling Reflection", "dB": 72.1443}, {"Freq": 19027.6, "Measurements": "Ceiling Reflection", "dB": 71.0274}, {"Freq": 19698.5, "Measurements": "Ceiling Reflection", "dB": 68.3594}, {"Freq": 19999.5, "Measurements": "Ceiling Reflection", "dB": 66.3657}, {"Freq": 20.5078, "Measurements": "Total Vertical Reflection", "dB": 51.3024}, {"Freq": 21.2402, "Measurements": "Total Vertical Reflection", "dB": 50.2175}, {"Freq": 21.9727, "Measurements": "Total Vertical Reflection", "dB": 52.4814}, {"Freq": 22.7051, "Measurements": "Total Vertical Reflection", "dB": 54.6803}, {"Freq": 23.4375, "Measurements": "Total Vertical Reflection", "dB": 58.9421}, {"Freq": 24.1699, "Measurements": "Total Vertical Reflection", "dB": 60.0959}, {"Freq": 25.6348, "Measurements": "Total Vertical Reflection", "dB": 64.0732}, {"Freq": 26.3672, "Measurements": "Total Vertical Reflection", "dB": 65.6548}, {"Freq": 27.0996, "Measurements": "Total Vertical Reflection", "dB": 67.6526}, {"Freq": 27.832, "Measurements": "Total Vertical Reflection", "dB": 69.3679}, {"Freq": 29.2969, "Measurements": "Total Vertical Reflection", "dB": 72.7379}, {"Freq": 30.0293, "Measurements": "Total Vertical Reflection", "dB": 74.3282}, {"Freq": 31.4941, "Measurements": "Total Vertical Reflection", "dB": 77.3281}, {"Freq": 32.2266, "Measurements": "Total Vertical Reflection", "dB": 78.7448}, {"Freq": 33.6914, "Measurements": "Total Vertical Reflection", "dB": 81.2858}, {"Freq": 34.4238, "Measurements": "Total Vertical Reflection", "dB": 82.465}, {"Freq": 35.8887, "Measurements": "Total Vertical Reflection", "dB": 84.6298}, {"Freq": 37.3535, "Measurements": "Total Vertical Reflection", "dB": 86.4783}, {"Freq": 38.8184, "Measurements": "Total Vertical Reflection", "dB": 87.9536}, {"Freq": 39.5508, "Measurements": "Total Vertical Reflection", "dB": 88.5264}, {"Freq": 41.0156, "Measurements": "Total Vertical Reflection", "dB": 89.5658}, {"Freq": 42.4805, "Measurements": "Total Vertical Reflection", "dB": 90.3855}, {"Freq": 43.9453, "Measurements": "Total Vertical Reflection", "dB": 90.9698}, {"Freq": 45.4102, "Measurements": "Total Vertical Reflection", "dB": 91.3661}, {"Freq": 47.6074, "Measurements": "Total Vertical Reflection", "dB": 91.8006}, {"Freq": 49.0723, "Measurements": "Total Vertical Reflection", "dB": 91.9822}, {"Freq": 50.5371, "Measurements": "Total Vertical Reflection", "dB": 92.1086}, {"Freq": 52.7344, "Measurements": "Total Vertical Reflection", "dB": 92.2627}, {"Freq": 54.1992, "Measurements": "Total Vertical Reflection", "dB": 92.3268}, {"Freq": 56.3965, "Measurements": "Total Vertical Reflection", "dB": 92.3798}, {"Freq": 58.5938, "Measurements": "Total Vertical Reflection", "dB": 92.4463}, {"Freq": 60.0586, "Measurements": "Total Vertical Reflection", "dB": 92.495}, {"Freq": 62.2559, "Measurements": "Total Vertical Reflection", "dB": 92.5151}, {"Freq": 64.4531, "Measurements": "Total Vertical Reflection", "dB": 92.5514}, {"Freq": 66.6504, "Measurements": "Total Vertical Reflection", "dB": 92.5765}, {"Freq": 69.5801, "Measurements": "Total Vertical Reflection", "dB": 92.6328}, {"Freq": 71.7773, "Measurements": "Total Vertical Reflection", "dB": 92.6582}, {"Freq": 73.9746, "Measurements": "Total Vertical Reflection", "dB": 92.7036}, {"Freq": 76.9043, "Measurements": "Total Vertical Reflection", "dB": 92.7232}, {"Freq": 79.834, "Measurements": "Total Vertical Reflection", "dB": 92.7978}, {"Freq": 82.7637, "Measurements": "Total Vertical Reflection", "dB": 92.9314}, {"Freq": 85.6934, "Measurements": "Total Vertical Reflection", "dB": 92.8619}, {"Freq": 88.623, "Measurements": "Total Vertical Reflection", "dB": 92.7674}, {"Freq": 91.5527, "Measurements": "Total Vertical Reflection", "dB": 92.7456}, {"Freq": 94.4824, "Measurements": "Total Vertical Reflection", "dB": 92.8329}, {"Freq": 98.1445, "Measurements": "Total Vertical Reflection", "dB": 92.9615}, {"Freq": 101.807, "Measurements": "Total Vertical Reflection", "dB": 92.9039}, {"Freq": 105.469, "Measurements": "Total Vertical Reflection", "dB": 92.8799}, {"Freq": 109.131, "Measurements": "Total Vertical Reflection", "dB": 92.9173}, {"Freq": 112.793, "Measurements": "Total Vertical Reflection", "dB": 92.7751}, {"Freq": 116.455, "Measurements": "Total Vertical Reflection", "dB": 92.7534}, {"Freq": 120.85, "Measurements": "Total Vertical Reflection", "dB": 92.9795}, {"Freq": 125.244, "Measurements": "Total Vertical Reflection", "dB": 92.8788}, {"Freq": 129.639, "Measurements": "Total Vertical Reflection", "dB": 92.7523}, {"Freq": 134.033, "Measurements": "Total Vertical Reflection", "dB": 92.6425}, {"Freq": 138.428, "Measurements": "Total Vertical Reflection", "dB": 92.4668}, {"Freq": 143.555, "Measurements": "Total Vertical Reflection", "dB": 92.3167}, {"Freq": 148.682, "Measurements": "Total Vertical Reflection", "dB": 92.2747}, {"Freq": 153.809, "Measurements": "Total Vertical Reflection", "dB": 92.1696}, {"Freq": 159.668, "Measurements": "Total Vertical Reflection", "dB": 92.0364}, {"Freq": 164.795, "Measurements": "Total Vertical Reflection", "dB": 91.5955}, {"Freq": 170.654, "Measurements": "Total Vertical Reflection", "dB": 91.7402}, {"Freq": 176.514, "Measurements": "Total Vertical Reflection", "dB": 91.9945}, {"Freq": 183.105, "Measurements": "Total Vertical Reflection", "dB": 92.1644}, {"Freq": 189.697, "Measurements": "Total Vertical Reflection", "dB": 92.4316}, {"Freq": 196.289, "Measurements": "Total Vertical Reflection", "dB": 92.3973}, {"Freq": 202.881, "Measurements": "Total Vertical Reflection", "dB": 92.4237}, {"Freq": 210.205, "Measurements": "Total Vertical Reflection", "dB": 92.3556}, {"Freq": 217.529, "Measurements": "Total Vertical Reflection", "dB": 92.2903}, {"Freq": 225.586, "Measurements": "Total Vertical Reflection", "dB": 92.3967}, {"Freq": 232.91, "Measurements": "Total Vertical Reflection", "dB": 92.6045}, {"Freq": 241.699, "Measurements": "Total Vertical Reflection", "dB": 92.5471}, {"Freq": 249.756, "Measurements": "Total Vertical Reflection", "dB": 92.8283}, {"Freq": 258.545, "Measurements": "Total Vertical Reflection", "dB": 92.807}, {"Freq": 268.066, "Measurements": "Total Vertical Reflection", "dB": 92.3371}, {"Freq": 277.588, "Measurements": "Total Vertical Reflection", "dB": 92.092}, {"Freq": 287.109, "Measurements": "Total Vertical Reflection", "dB": 91.6034}, {"Freq": 297.363, "Measurements": "Total Vertical Reflection", "dB": 91.4844}, {"Freq": 307.617, "Measurements": "Total Vertical Reflection", "dB": 90.6995}, {"Freq": 318.604, "Measurements": "Total Vertical Reflection", "dB": 90.3309}, {"Freq": 329.59, "Measurements": "Total Vertical Reflection", "dB": 90.8085}, {"Freq": 341.309, "Measurements": "Total Vertical Reflection", "dB": 90.3681}, {"Freq": 353.76, "Measurements": "Total Vertical Reflection", "dB": 90.6922}, {"Freq": 366.211, "Measurements": "Total Vertical Reflection", "dB": 90.9384}, {"Freq": 378.662, "Measurements": "Total Vertical Reflection", "dB": 91.4219}, {"Freq": 392.578, "Measurements": "Total Vertical Reflection", "dB": 91.4282}, {"Freq": 405.762, "Measurements": "Total Vertical Reflection", "dB": 91.3779}, {"Freq": 420.41, "Measurements": "Total Vertical Reflection", "dB": 92.1515}, {"Freq": 435.059, "Measurements": "Total Vertical Reflection", "dB": 91.5715}, {"Freq": 450.439, "Measurements": "Total Vertical Reflection", "dB": 91.7451}, {"Freq": 466.553, "Measurements": "Total Vertical Reflection", "dB": 91.7757}, {"Freq": 482.666, "Measurements": "Total Vertical Reflection", "dB": 91.5519}, {"Freq": 500.244, "Measurements": "Total Vertical Reflection", "dB": 91.5238}, {"Freq": 517.822, "Measurements": "Total Vertical Reflection", "dB": 91.4685}, {"Freq": 536.133, "Measurements": "Total Vertical Reflection", "dB": 91.6822}, {"Freq": 554.443, "Measurements": "Total Vertical Reflection", "dB": 91.2702}, {"Freq": 574.219, "Measurements": "Total Vertical Reflection", "dB": 91.8298}, {"Freq": 594.727, "Measurements": "Total Vertical Reflection", "dB": 91.707}, {"Freq": 615.234, "Measurements": "Total Vertical Reflection", "dB": 91.7757}, {"Freq": 637.207, "Measurements": "Total Vertical Reflection", "dB": 91.9431}, {"Freq": 659.912, "Measurements": "Total Vertical Reflection", "dB": 91.6378}, {"Freq": 683.35, "Measurements": "Total Vertical Reflection", "dB": 91.9973}, {"Freq": 706.787, "Measurements": "Total Vertical Reflection", "dB": 91.9781}, {"Freq": 731.689, "Measurements": "Total Vertical Reflection", "dB": 92.0022}, {"Freq": 758.057, "Measurements": "Total Vertical Reflection", "dB": 91.9547}, {"Freq": 784.424, "Measurements": "Total Vertical Reflection", "dB": 91.6805}, {"Freq": 812.256, "Measurements": "Total Vertical Reflection", "dB": 91.2223}, {"Freq": 840.82, "Measurements": "Total Vertical Reflection", "dB": 91.1058}, {"Freq": 870.85, "Measurements": "Total Vertical Reflection", "dB": 91.877}, {"Freq": 901.611, "Measurements": "Total Vertical Reflection", "dB": 91.9962}, {"Freq": 933.105, "Measurements": "Total Vertical Reflection", "dB": 92.403}, {"Freq": 966.064, "Measurements": "Total Vertical Reflection", "dB": 92.9466}, {"Freq": 999.756, "Measurements": "Total Vertical Reflection", "dB": 92.7425}, {"Freq": 1034.91, "Measurements": "Total Vertical Reflection", "dB": 92.7356}, {"Freq": 1071.53, "Measurements": "Total Vertical Reflection", "dB": 92.5626}, {"Freq": 1109.62, "Measurements": "Total Vertical Reflection", "dB": 92.3074}, {"Freq": 1148.44, "Measurements": "Total Vertical Reflection", "dB": 92.0104}, {"Freq": 1189.45, "Measurements": "Total Vertical Reflection", "dB": 91.9877}, {"Freq": 1231.2, "Measurements": "Total Vertical Reflection", "dB": 91.7724}, {"Freq": 1274.41, "Measurements": "Total Vertical Reflection", "dB": 91.1473}, {"Freq": 1319.82, "Measurements": "Total Vertical Reflection", "dB": 91.1588}, {"Freq": 1365.97, "Measurements": "Total Vertical Reflection", "dB": 90.5698}, {"Freq": 1414.31, "Measurements": "Total Vertical Reflection", "dB": 90.4141}, {"Freq": 1464.11, "Measurements": "Total Vertical Reflection", "dB": 89.7192}, {"Freq": 1515.38, "Measurements": "Total Vertical Reflection", "dB": 89.4835}, {"Freq": 1568.85, "Measurements": "Total Vertical Reflection", "dB": 89.9645}, {"Freq": 1624.51, "Measurements": "Total Vertical Reflection", "dB": 88.9973}, {"Freq": 1681.64, "Measurements": "Total Vertical Reflection", "dB": 89.4989}, {"Freq": 1740.97, "Measurements": "Total Vertical Reflection", "dB": 88.7379}, {"Freq": 1802.49, "Measurements": "Total Vertical Reflection", "dB": 88.3886}, {"Freq": 1866.21, "Measurements": "Total Vertical Reflection", "dB": 88.4397}, {"Freq": 1932.13, "Measurements": "Total Vertical Reflection", "dB": 88.4434}, {"Freq": 2000.24, "Measurements": "Total Vertical Reflection", "dB": 87.462}, {"Freq": 2070.56, "Measurements": "Total Vertical Reflection", "dB": 87.7824}, {"Freq": 2143.8, "Measurements": "Total Vertical Reflection", "dB": 88.8225}, {"Freq": 2219.24, "Measurements": "Total Vertical Reflection", "dB": 89.3411}, {"Freq": 2297.61, "Measurements": "Total Vertical Reflection", "dB": 89.3013}, {"Freq": 2378.17, "Measurements": "Total Vertical Reflection", "dB": 89.4077}, {"Freq": 2462.4, "Measurements": "Total Vertical Reflection", "dB": 89.5604}, {"Freq": 2548.83, "Measurements": "Total Vertical Reflection", "dB": 89.1657}, {"Freq": 2638.92, "Measurements": "Total Vertical Reflection", "dB": 88.8941}, {"Freq": 2731.93, "Measurements": "Total Vertical Reflection", "dB": 88.5285}, {"Freq": 2828.61, "Measurements": "Total Vertical Reflection", "dB": 88.0554}, {"Freq": 2928.22, "Measurements": "Total Vertical Reflection", "dB": 87.8127}, {"Freq": 3031.49, "Measurements": "Total Vertical Reflection", "dB": 87.5807}, {"Freq": 3138.43, "Measurements": "Total Vertical Reflection", "dB": 87.4735}, {"Freq": 3249.02, "Measurements": "Total Vertical Reflection", "dB": 87.4388}, {"Freq": 3363.28, "Measurements": "Total Vertical Reflection", "dB": 87.4258}, {"Freq": 3481.93, "Measurements": "Total Vertical Reflection", "dB": 87.4848}, {"Freq": 3604.98, "Measurements": "Total Vertical Reflection", "dB": 87.7007}, {"Freq": 3732.42, "Measurements": "Total Vertical Reflection", "dB": 87.8938}, {"Freq": 3863.53, "Measurements": "Total Vertical Reflection", "dB": 87.8673}, {"Freq": 3999.76, "Measurements": "Total Vertical Reflection", "dB": 87.88}, {"Freq": 4141.11, "Measurements": "Total Vertical Reflection", "dB": 87.7812}, {"Freq": 4286.87, "Measurements": "Total Vertical Reflection", "dB": 88.0303}, {"Freq": 4438.48, "Measurements": "Total Vertical Reflection", "dB": 88.2052}, {"Freq": 4594.48, "Measurements": "Total Vertical Reflection", "dB": 88.3388}, {"Freq": 4757.08, "Measurements": "Total Vertical Reflection", "dB": 88.2898}, {"Freq": 4924.8, "Measurements": "Total Vertical Reflection", "dB": 87.6673}, {"Freq": 5098.39, "Measurements": "Total Vertical Reflection", "dB": 86.6663}, {"Freq": 5277.83, "Measurements": "Total Vertical Reflection", "dB": 86.5722}, {"Freq": 5463.87, "Measurements": "Total Vertical Reflection", "dB": 87.9155}, {"Freq": 5656.49, "Measurements": "Total Vertical Reflection", "dB": 88.5731}, {"Freq": 5856.45, "Measurements": "Total Vertical Reflection", "dB": 89.0585}, {"Freq": 6062.99, "Measurements": "Total Vertical Reflection", "dB": 89.187}, {"Freq": 6276.86, "Measurements": "Total Vertical Reflection", "dB": 89.139}, {"Freq": 6498.05, "Measurements": "Total Vertical Reflection", "dB": 88.8471}, {"Freq": 6727.29, "Measurements": "Total Vertical Reflection", "dB": 88.7724}, {"Freq": 6964.6, "Measurements": "Total Vertical Reflection", "dB": 89.2682}, {"Freq": 7209.96, "Measurements": "Total Vertical Reflection", "dB": 89.5218}, {"Freq": 7464.11, "Measurements": "Total Vertical Reflection", "dB": 89.7651}, {"Freq": 7727.78, "Measurements": "Total Vertical Reflection", "dB": 88.8688}, {"Freq": 8000.24, "Measurements": "Total Vertical Reflection", "dB": 88.1705}, {"Freq": 8282.23, "Measurements": "Total Vertical Reflection", "dB": 87.3769}, {"Freq": 8574.46, "Measurements": "Total Vertical Reflection", "dB": 86.582}, {"Freq": 8876.22, "Measurements": "Total Vertical Reflection", "dB": 86.4414}, {"Freq": 9189.7, "Measurements": "Total Vertical Reflection", "dB": 86.1689}, {"Freq": 9513.43, "Measurements": "Total Vertical Reflection", "dB": 85.9169}, {"Freq": 9848.88, "Measurements": "Total Vertical Reflection", "dB": 86.1572}, {"Freq": 10196.8, "Measurements": "Total Vertical Reflection", "dB": 86.8029}, {"Freq": 10556.4, "Measurements": "Total Vertical Reflection", "dB": 87.168}, {"Freq": 10928.5, "Measurements": "Total Vertical Reflection", "dB": 86.8798}, {"Freq": 11313.7, "Measurements": "Total Vertical Reflection", "dB": 86.4155}, {"Freq": 11712.9, "Measurements": "Total Vertical Reflection", "dB": 86.1976}, {"Freq": 12126.0, "Measurements": "Total Vertical Reflection", "dB": 86.1009}, {"Freq": 12553.7, "Measurements": "Total Vertical Reflection", "dB": 86.4526}, {"Freq": 12996.1, "Measurements": "Total Vertical Reflection", "dB": 86.9077}, {"Freq": 13454.6, "Measurements": "Total Vertical Reflection", "dB": 87.1583}, {"Freq": 13928.5, "Measurements": "Total Vertical Reflection", "dB": 87.0487}, {"Freq": 14419.9, "Measurements": "Total Vertical Reflection", "dB": 87.0209}, {"Freq": 14928.2, "Measurements": "Total Vertical Reflection", "dB": 86.8402}, {"Freq": 15454.8, "Measurements": "Total Vertical Reflection", "dB": 86.4927}, {"Freq": 15999.8, "Measurements": "Total Vertical Reflection", "dB": 86.0649}, {"Freq": 16564.5, "Measurements": "Total Vertical Reflection", "dB": 85.0129}, {"Freq": 17148.2, "Measurements": "Total Vertical Reflection", "dB": 83.3968}, {"Freq": 17753.2, "Measurements": "Total Vertical Reflection", "dB": 81.9164}, {"Freq": 18379.4, "Measurements": "Total Vertical Reflection", "dB": 81.1067}, {"Freq": 19027.6, "Measurements": "Total Vertical Reflection", "dB": 79.7872}, {"Freq": 19698.5, "Measurements": "Total Vertical Reflection", "dB": 78.0398}, {"Freq": 19999.5, "Measurements": "Total Vertical Reflection", "dB": 77.2085}]}}