{"config": {"view": {"continuousWidth": 400, "continuousHeight": 300}}, "layer": [{"mark": {"type": "line", "interpolate": "basis"}, "encoding": {"color": {"type": "nominal", "field": "Measurements", "sort": null}, "x": {"type": "quantitative", "field": "Freq", "scale": {"domain": [20, 20000], "type": "log"}}, "y": {"type": "quantitative", "field": "dB", "scale": {"zero": false}}}, "height": 600, "width": 1200}, {"mark": "point", "encoding": {"opacity": {"value": 0}, "x": {"type": "quantitative", "field": "Freq"}}, "selection": {"selector001": {"type": "single", "nearest": true, "on": "mouseover", "fields": ["Freq"], "empty": "none"}}}, {"mark": "point", "encoding": {"color": {"type": "nominal", "field": "Measurements", "sort": null}, "opacity": {"condition": {"value": 1, "selection": "selector001"}, "value": 0}, "x": {"type": "quantitative", "field": "Freq", "scale": {"domain": [20, 20000], "type": "log"}}, "y": {"type": "quantitative", "field": "dB", "scale": {"zero": false}}}, "height": 600, "width": 1200}, {"mark": {"type": "rule", "color": "gray"}, "encoding": {"x": {"type": "quantitative", "field": "Freq"}}, "transform": [{"filter": {"selection": "selector001"}}]}, {"mark": {"type": "text", "align": "left", "dx": 5, "dy": -5}, "encoding": {"color": {"type": "nominal", "field": "Measurements", "sort": null}, "text": {"condition": {"type": "quantitative", "field": "dB", "selection": "selector001"}, "value": " "}, "x": {"type": "quantitative", "field": "Freq", "scale": {"domain": [20, 20000], "type": "log"}}, "y": {"type": "quantitative", "field": "dB", "scale": {"zero": false}}}, "height": 600, "width": 1200}], "data": {"name": "data-bfd0d36ec187db747a3da0ea5a6eaf24"}, "$schema": "https://vega.github.io/schema/vega-lite/v4.0.2.json", "datasets": {"data-bfd0d36ec187db747a3da0ea5a6eaf24": [{"Freq": 20.5078, "Measurements": "Floor Reflection", "dB": 42.8141}, {"Freq": 21.2402, "Measurements": "Floor Reflection", "dB": 43.1245}, {"Freq": 21.9727, "Measurements": "Floor Reflection", "dB": 45.2949}, {"Freq": 22.7051, "Measurements": "Floor Reflection", "dB": 45.5514}, {"Freq": 23.4375, "Measurements": "Floor Reflection", "dB": 46.0466}, {"Freq": 24.1699, "Measurements": "Floor Reflection", "dB": 46.9127}, {"Freq": 25.6348, "Measurements": "Floor Reflection", "dB": 48.4722}, {"Freq": 26.3672, "Measurements": "Floor Reflection", "dB": 49.1807}, {"Freq": 27.0996, "Measurements": "Floor Reflection", "dB": 49.873}, {"Freq": 27.832, "Measurements": "Floor Reflection", "dB": 50.9721}, {"Freq": 29.2969, "Measurements": "Floor Reflection", "dB": 52.655}, {"Freq": 30.0293, "Measurements": "Floor Reflection", "dB": 53.0042}, {"Freq": 31.4941, "Measurements": "Floor Reflection", "dB": 54.6596}, {"Freq": 32.2266, "Measurements": "Floor Reflection", "dB": 55.1944}, {"Freq": 33.6914, "Measurements": "Floor Reflection", "dB": 56.6345}, {"Freq": 34.4238, "Measurements": "Floor Reflection", "dB": 56.9818}, {"Freq": 35.8887, "Measurements": "Floor Reflection", "dB": 58.3091}, {"Freq": 37.3535, "Measurements": "Floor Reflection", "dB": 59.8731}, {"Freq": 38.8184, "Measurements": "Floor Reflection", "dB": 61.3282}, {"Freq": 39.5508, "Measurements": "Floor Reflection", "dB": 62.0095}, {"Freq": 41.0156, "Measurements": "Floor Reflection", "dB": 63.2222}, {"Freq": 42.4805, "Measurements": "Floor Reflection", "dB": 64.5474}, {"Freq": 43.9453, "Measurements": "Floor Reflection", "dB": 66.0199}, {"Freq": 45.4102, "Measurements": "Floor Reflection", "dB": 67.2917}, {"Freq": 47.6074, "Measurements": "Floor Reflection", "dB": 69.2644}, {"Freq": 49.0723, "Measurements": "Floor Reflection", "dB": 70.5629}, {"Freq": 50.5371, "Measurements": "Floor Reflection", "dB": 71.8264}, {"Freq": 52.7344, "Measurements": "Floor Reflection", "dB": 73.77}, {"Freq": 54.1992, "Measurements": "Floor Reflection", "dB": 75.0584}, {"Freq": 56.3965, "Measurements": "Floor Reflection", "dB": 76.9007}, {"Freq": 58.5938, "Measurements": "Floor Reflection", "dB": 78.5538}, {"Freq": 60.0586, "Measurements": "Floor Reflection", "dB": 79.6096}, {"Freq": 62.2559, "Measurements": "Floor Reflection", "dB": 81.0692}, {"Freq": 64.4531, "Measurements": "Floor Reflection", "dB": 82.2691}, {"Freq": 66.6504, "Measurements": "Floor Reflection", "dB": 83.2245}, {"Freq": 69.5801, "Measurements": "Floor Reflection", "dB": 84.0376}, {"Freq": 71.7773, "Measurements": "Floor Reflection", "dB": 84.3521}, {"Freq": 73.9746, "Measurements": "Floor Reflection", "dB": 84.4442}, {"Freq": 76.9043, "Measurements": "Floor Reflection", "dB": 84.3698}, {"Freq": 79.834, "Measurements": "Floor Reflection", "dB": 84.1716}, {"Freq": 82.7637, "Measurements": "Floor Reflection", "dB": 83.9916}, {"Freq": 85.6934, "Measurements": "Floor Reflection", "dB": 83.8031}, {"Freq": 88.623, "Measurements": "Floor Reflection", "dB": 83.6218}, {"Freq": 91.5527, "Measurements": "Floor Reflection", "dB": 83.3766}, {"Freq": 94.4824, "Measurements": "Floor Reflection", "dB": 83.1965}, {"Freq": 98.1445, "Measurements": "Floor Reflection", "dB": 83.2122}, {"Freq": 101.807, "Measurements": "Floor Reflection", "dB": 83.1454}, {"Freq": 105.469, "Measurements": "Floor Reflection", "dB": 83.0866}, {"Freq": 109.131, "Measurements": "Floor Reflection", "dB": 83.1523}, {"Freq": 112.793, "Measurements": "Floor Reflection", "dB": 83.2327}, {"Freq": 116.455, "Measurements": "Floor Reflection", "dB": 83.2293}, {"Freq": 120.85, "Measurements": "Floor Reflection", "dB": 83.3539}, {"Freq": 125.244, "Measurements": "Floor Reflection", "dB": 83.5253}, {"Freq": 129.639, "Measurements": "Floor Reflection", "dB": 83.5288}, {"Freq": 134.033, "Measurements": "Floor Reflection", "dB": 83.5235}, {"Freq": 138.428, "Measurements": "Floor Reflection", "dB": 83.6614}, {"Freq": 143.555, "Measurements": "Floor Reflection", "dB": 83.8047}, {"Freq": 148.682, "Measurements": "Floor Reflection", "dB": 83.9455}, {"Freq": 153.809, "Measurements": "Floor Reflection", "dB": 84.0113}, {"Freq": 159.668, "Measurements": "Floor Reflection", "dB": 84.1887}, {"Freq": 164.795, "Measurements": "Floor Reflection", "dB": 84.3354}, {"Freq": 170.654, "Measurements": "Floor Reflection", "dB": 84.3817}, {"Freq": 176.514, "Measurements": "Floor Reflection", "dB": 84.3633}, {"Freq": 183.105, "Measurements": "Floor Reflection", "dB": 84.3544}, {"Freq": 189.697, "Measurements": "Floor Reflection", "dB": 84.3748}, {"Freq": 196.289, "Measurements": "Floor Reflection", "dB": 84.4037}, {"Freq": 202.881, "Measurements": "Floor Reflection", "dB": 84.4592}, {"Freq": 210.205, "Measurements": "Floor Reflection", "dB": 84.4309}, {"Freq": 217.529, "Measurements": "Floor Reflection", "dB": 84.4255}, {"Freq": 225.586, "Measurements": "Floor Reflection", "dB": 84.4234}, {"Freq": 232.91, "Measurements": "Floor Reflection", "dB": 84.5775}, {"Freq": 241.699, "Measurements": "Floor Reflection", "dB": 84.3928}, {"Freq": 249.756, "Measurements": "Floor Reflection", "dB": 84.573}, {"Freq": 258.545, "Measurements": "Floor Reflection", "dB": 84.4025}, {"Freq": 268.066, "Measurements": "Floor Reflection", "dB": 84.2065}, {"Freq": 277.588, "Measurements": "Floor Reflection", "dB": 84.207}, {"Freq": 287.109, "Measurements": "Floor Reflection", "dB": 84.0216}, {"Freq": 297.363, "Measurements": "Floor Reflection", "dB": 83.8902}, {"Freq": 307.617, "Measurements": "Floor Reflection", "dB": 83.8619}, {"Freq": 318.604, "Measurements": "Floor Reflection", "dB": 83.7427}, {"Freq": 329.59, "Measurements": "Floor Reflection", "dB": 83.9524}, {"Freq": 341.309, "Measurements": "Floor Reflection", "dB": 83.8616}, {"Freq": 353.76, "Measurements": "Floor Reflection", "dB": 84.4046}, {"Freq": 366.211, "Measurements": "Floor Reflection", "dB": 84.3052}, {"Freq": 378.662, "Measurements": "Floor Reflection", "dB": 84.474}, {"Freq": 392.578, "Measurements": "Floor Reflection", "dB": 84.0718}, {"Freq": 405.762, "Measurements": "Floor Reflection", "dB": 84.1122}, {"Freq": 420.41, "Measurements": "Floor Reflection", "dB": 84.3334}, {"Freq": 435.059, "Measurements": "Floor Reflection", "dB": 83.8049}, {"Freq": 450.439, "Measurements": "Floor Reflection", "dB": 83.8626}, {"Freq": 466.553, "Measurements": "Floor Reflection", "dB": 83.4738}, {"Freq": 482.666, "Measurements": "Floor Reflection", "dB": 83.3721}, {"Freq": 500.244, "Measurements": "Floor Reflection", "dB": 83.9305}, {"Freq": 517.822, "Measurements": "Floor Reflection", "dB": 83.4355}, {"Freq": 536.133, "Measurements": "Floor Reflection", "dB": 83.9054}, {"Freq": 554.443, "Measurements": "Floor Reflection", "dB": 84.5743}, {"Freq": 574.219, "Measurements": "Floor Reflection", "dB": 83.9349}, {"Freq": 594.727, "Measurements": "Floor Reflection", "dB": 83.0384}, {"Freq": 615.234, "Measurements": "Floor Reflection", "dB": 83.6359}, {"Freq": 637.207, "Measurements": "Floor Reflection", "dB": 83.8391}, {"Freq": 659.912, "Measurements": "Floor Reflection", "dB": 83.6094}, {"Freq": 683.35, "Measurements": "Floor Reflection", "dB": 84.0231}, {"Freq": 706.787, "Measurements": "Floor Reflection", "dB": 84.2181}, {"Freq": 731.689, "Measurements": "Floor Reflection", "dB": 84.2681}, {"Freq": 758.057, "Measurements": "Floor Reflection", "dB": 84.774}, {"Freq": 784.424, "Measurements": "Floor Reflection", "dB": 84.513}, {"Freq": 812.256, "Measurements": "Floor Reflection", "dB": 84.5151}, {"Freq": 840.82, "Measurements": "Floor Reflection", "dB": 84.3423}, {"Freq": 870.85, "Measurements": "Floor Reflection", "dB": 83.871}, {"Freq": 901.611, "Measurements": "Floor Reflection", "dB": 84.0962}, {"Freq": 933.105, "Measurements": "Floor Reflection", "dB": 84.0513}, {"Freq": 966.064, "Measurements": "Floor Reflection", "dB": 84.0932}, {"Freq": 999.756, "Measurements": "Floor Reflection", "dB": 83.8207}, {"Freq": 1034.91, "Measurements": "Floor Reflection", "dB": 84.233}, {"Freq": 1071.53, "Measurements": "Floor Reflection", "dB": 84.5113}, {"Freq": 1109.62, "Measurements": "Floor Reflection", "dB": 84.908}, {"Freq": 1148.44, "Measurements": "Floor Reflection", "dB": 84.9058}, {"Freq": 1189.45, "Measurements": "Floor Reflection", "dB": 84.3214}, {"Freq": 1231.2, "Measurements": "Floor Reflection", "dB": 84.4647}, {"Freq": 1274.41, "Measurements": "Floor Reflection", "dB": 84.289}, {"Freq": 1319.82, "Measurements": "Floor Reflection", "dB": 84.4393}, {"Freq": 1365.97, "Measurements": "Floor Reflection", "dB": 84.1353}, {"Freq": 1414.31, "Measurements": "Floor Reflection", "dB": 84.4331}, {"Freq": 1464.11, "Measurements": "Floor Reflection", "dB": 84.8147}, {"Freq": 1515.38, "Measurements": "Floor Reflection", "dB": 85.7423}, {"Freq": 1568.85, "Measurements": "Floor Reflection", "dB": 84.7892}, {"Freq": 1624.51, "Measurements": "Floor Reflection", "dB": 85.471}, {"Freq": 1681.64, "Measurements": "Floor Reflection", "dB": 85.5982}, {"Freq": 1740.97, "Measurements": "Floor Reflection", "dB": 84.7661}, {"Freq": 1802.49, "Measurements": "Floor Reflection", "dB": 84.6999}, {"Freq": 1866.21, "Measurements": "Floor Reflection", "dB": 83.9999}, {"Freq": 1932.13, "Measurements": "Floor Reflection", "dB": 83.6064}, {"Freq": 2000.24, "Measurements": "Floor Reflection", "dB": 83.2644}, {"Freq": 2070.56, "Measurements": "Floor Reflection", "dB": 82.161}, {"Freq": 2143.8, "Measurements": "Floor Reflection", "dB": 81.2305}, {"Freq": 2219.24, "Measurements": "Floor Reflection", "dB": 79.5918}, {"Freq": 2297.61, "Measurements": "Floor Reflection", "dB": 79.4073}, {"Freq": 2378.17, "Measurements": "Floor Reflection", "dB": 79.1092}, {"Freq": 2462.4, "Measurements": "Floor Reflection", "dB": 78.3204}, {"Freq": 2548.83, "Measurements": "Floor Reflection", "dB": 78.1273}, {"Freq": 2638.92, "Measurements": "Floor Reflection", "dB": 78.5585}, {"Freq": 2731.93, "Measurements": "Floor Reflection", "dB": 77.8578}, {"Freq": 2828.61, "Measurements": "Floor Reflection", "dB": 78.1514}, {"Freq": 2928.22, "Measurements": "Floor Reflection", "dB": 77.9739}, {"Freq": 3031.49, "Measurements": "Floor Reflection", "dB": 77.2751}, {"Freq": 3138.43, "Measurements": "Floor Reflection", "dB": 78.4019}, {"Freq": 3249.02, "Measurements": "Floor Reflection", "dB": 79.3792}, {"Freq": 3363.28, "Measurements": "Floor Reflection", "dB": 79.36}, {"Freq": 3481.93, "Measurements": "Floor Reflection", "dB": 79.691}, {"Freq": 3604.98, "Measurements": "Floor Reflection", "dB": 79.909}, {"Freq": 3732.42, "Measurements": "Floor Reflection", "dB": 80.1111}, {"Freq": 3863.53, "Measurements": "Floor Reflection", "dB": 80.0346}, {"Freq": 3999.76, "Measurements": "Floor Reflection", "dB": 79.6557}, {"Freq": 4141.11, "Measurements": "Floor Reflection", "dB": 79.0413}, {"Freq": 4286.87, "Measurements": "Floor Reflection", "dB": 78.7517}, {"Freq": 4438.48, "Measurements": "Floor Reflection", "dB": 79.2769}, {"Freq": 4594.48, "Measurements": "Floor Reflection", "dB": 79.6119}, {"Freq": 4757.08, "Measurements": "Floor Reflection", "dB": 80.0933}, {"Freq": 4924.8, "Measurements": "Floor Reflection", "dB": 80.5517}, {"Freq": 5098.39, "Measurements": "Floor Reflection", "dB": 80.8463}, {"Freq": 5277.83, "Measurements": "Floor Reflection", "dB": 81.4392}, {"Freq": 5463.87, "Measurements": "Floor Reflection", "dB": 81.3158}, {"Freq": 5656.49, "Measurements": "Floor Reflection", "dB": 81.7594}, {"Freq": 5856.45, "Measurements": "Floor Reflection", "dB": 81.8059}, {"Freq": 6062.99, "Measurements": "Floor Reflection", "dB": 81.9876}, {"Freq": 6276.86, "Measurements": "Floor Reflection", "dB": 81.7423}, {"Freq": 6498.05, "Measurements": "Floor Reflection", "dB": 81.2405}, {"Freq": 6727.29, "Measurements": "Floor Reflection", "dB": 80.875}, {"Freq": 6964.6, "Measurements": "Floor Reflection", "dB": 80.4849}, {"Freq": 7209.96, "Measurements": "Floor Reflection", "dB": 80.5788}, {"Freq": 7464.11, "Measurements": "Floor Reflection", "dB": 80.3617}, {"Freq": 7727.78, "Measurements": "Floor Reflection", "dB": 79.8589}, {"Freq": 8000.24, "Measurements": "Floor Reflection", "dB": 79.2738}, {"Freq": 8282.23, "Measurements": "Floor Reflection", "dB": 78.8917}, {"Freq": 8574.46, "Measurements": "Floor Reflection", "dB": 79.2898}, {"Freq": 8876.22, "Measurements": "Floor Reflection", "dB": 79.9657}, {"Freq": 9189.7, "Measurements": "Floor Reflection", "dB": 80.5708}, {"Freq": 9513.43, "Measurements": "Floor Reflection", "dB": 80.5282}, {"Freq": 9848.88, "Measurements": "Floor Reflection", "dB": 80.488}, {"Freq": 10196.8, "Measurements": "Floor Reflection", "dB": 80.204}, {"Freq": 10556.4, "Measurements": "Floor Reflection", "dB": 80.2788}, {"Freq": 10928.5, "Measurements": "Floor Reflection", "dB": 80.537}, {"Freq": 11313.7, "Measurements": "Floor Reflection", "dB": 80.4373}, {"Freq": 11712.9, "Measurements": "Floor Reflection", "dB": 79.8509}, {"Freq": 12126.0, "Measurements": "Floor Reflection", "dB": 79.1555}, {"Freq": 12553.7, "Measurements": "Floor Reflection", "dB": 79.1129}, {"Freq": 12996.1, "Measurements": "Floor Reflection", "dB": 79.3403}, {"Freq": 13454.6, "Measurements": "Floor Reflection", "dB": 79.2946}, {"Freq": 13928.5, "Measurements": "Floor Reflection", "dB": 79.6002}, {"Freq": 14419.9, "Measurements": "Floor Reflection", "dB": 79.449}, {"Freq": 14928.2, "Measurements": "Floor Reflection", "dB": 79.5654}, {"Freq": 15454.8, "Measurements": "Floor Reflection", "dB": 79.3511}, {"Freq": 15999.8, "Measurements": "Floor Reflection", "dB": 78.592}, {"Freq": 16564.5, "Measurements": "Floor Reflection", "dB": 77.3303}, {"Freq": 17148.2, "Measurements": "Floor Reflection", "dB": 76.3297}, {"Freq": 17753.2, "Measurements": "Floor Reflection", "dB": 75.7361}, {"Freq": 18379.4, "Measurements": "Floor Reflection", "dB": 74.4554}, {"Freq": 19027.6, "Measurements": "Floor Reflection", "dB": 72.4687}, {"Freq": 19698.5, "Measurements": "Floor Reflection", "dB": 71.3686}, {"Freq": 19999.5, "Measurements": "Floor Reflection", "dB": 71.5785}, {"Freq": 20.5078, "Measurements": "Ceiling Reflection", "dB": 38.1751}, {"Freq": 21.2402, "Measurements": "Ceiling Reflection", "dB": 41.8769}, {"Freq": 21.9727, "Measurements": "Ceiling Reflection", "dB": 41.5896}, {"Freq": 22.7051, "Measurements": "Ceiling Reflection", "dB": 40.1497}, {"Freq": 23.4375, "Measurements": "Ceiling Reflection", "dB": 44.9788}, {"Freq": 24.1699, "Measurements": "Ceiling Reflection", "dB": 44.7014}, {"Freq": 25.6348, "Measurements": "Ceiling Reflection", "dB": 46.2664}, {"Freq": 26.3672, "Measurements": "Ceiling Reflection", "dB": 47.2382}, {"Freq": 27.0996, "Measurements": "Ceiling Reflection", "dB": 48.6117}, {"Freq": 27.832, "Measurements": "Ceiling Reflection", "dB": 49.4608}, {"Freq": 29.2969, "Measurements": "Ceiling Reflection", "dB": 51.1784}, {"Freq": 30.0293, "Measurements": "Ceiling Reflection", "dB": 51.4703}, {"Freq": 31.4941, "Measurements": "Ceiling Reflection", "dB": 53.3452}, {"Freq": 32.2266, "Measurements": "Ceiling Reflection", "dB": 54.0712}, {"Freq": 33.6914, "Measurements": "Ceiling Reflection", "dB": 55.4701}, {"Freq": 34.4238, "Measurements": "Ceiling Reflection", "dB": 55.8848}, {"Freq": 35.8887, "Measurements": "Ceiling Reflection", "dB": 57.4853}, {"Freq": 37.3535, "Measurements": "Ceiling Reflection", "dB": 59.1905}, {"Freq": 38.8184, "Measurements": "Ceiling Reflection", "dB": 60.6935}, {"Freq": 39.5508, "Measurements": "Ceiling Reflection", "dB": 61.3763}, {"Freq": 41.0156, "Measurements": "Ceiling Reflection", "dB": 62.638}, {"Freq": 42.4805, "Measurements": "Ceiling Reflection", "dB": 64.0023}, {"Freq": 43.9453, "Measurements": "Ceiling Reflection", "dB": 65.484}, {"Freq": 45.4102, "Measurements": "Ceiling Reflection", "dB": 66.7681}, {"Freq": 47.6074, "Measurements": "Ceiling Reflection", "dB": 68.7999}, {"Freq": 49.0723, "Measurements": "Ceiling Reflection", "dB": 70.1178}, {"Freq": 50.5371, "Measurements": "Ceiling Reflection", "dB": 71.4014}, {"Freq": 52.7344, "Measurements": "Ceiling Reflection", "dB": 73.3479}, {"Freq": 54.1992, "Measurements": "Ceiling Reflection", "dB": 74.6483}, {"Freq": 56.3965, "Measurements": "Ceiling Reflection", "dB": 76.4895}, {"Freq": 58.5938, "Measurements": "Ceiling Reflection", "dB": 78.1376}, {"Freq": 60.0586, "Measurements": "Ceiling Reflection", "dB": 79.2012}, {"Freq": 62.2559, "Measurements": "Ceiling Reflection", "dB": 80.649}, {"Freq": 64.4531, "Measurements": "Ceiling Reflection", "dB": 81.8539}, {"Freq": 66.6504, "Measurements": "Ceiling Reflection", "dB": 82.8207}, {"Freq": 69.5801, "Measurements": "Ceiling Reflection", "dB": 83.6493}, {"Freq": 71.7773, "Measurements": "Ceiling Reflection", "dB": 83.9821}, {"Freq": 73.9746, "Measurements": "Ceiling Reflection", "dB": 84.0959}, {"Freq": 76.9043, "Measurements": "Ceiling Reflection", "dB": 84.0445}, {"Freq": 79.834, "Measurements": "Ceiling Reflection", "dB": 83.8636}, {"Freq": 82.7637, "Measurements": "Ceiling Reflection", "dB": 83.6918}, {"Freq": 85.6934, "Measurements": "Ceiling Reflection", "dB": 83.5086}, {"Freq": 88.623, "Measurements": "Ceiling Reflection", "dB": 83.335}, {"Freq": 91.5527, "Measurements": "Ceiling Reflection", "dB": 83.0875}, {"Freq": 94.4824, "Measurements": "Ceiling Reflection", "dB": 82.9148}, {"Freq": 98.1445, "Measurements": "Ceiling Reflection", "dB": 82.9427}, {"Freq": 101.807, "Measurements": "Ceiling Reflection", "dB": 82.8905}, {"Freq": 105.469, "Measurements": "Ceiling Reflection", "dB": 82.8466}, {"Freq": 109.131, "Measurements": "Ceiling Reflection", "dB": 82.9119}, {"Freq": 112.793, "Measurements": "Ceiling Reflection", "dB": 82.9911}, {"Freq": 116.455, "Measurements": "Ceiling Reflection", "dB": 82.9981}, {"Freq": 120.85, "Measurements": "Ceiling Reflection", "dB": 83.1116}, {"Freq": 125.244, "Measurements": "Ceiling Reflection", "dB": 83.2302}, {"Freq": 129.639, "Measurements": "Ceiling Reflection", "dB": 83.2606}, {"Freq": 134.033, "Measurements": "Ceiling Reflection", "dB": 83.2375}, {"Freq": 138.428, "Measurements": "Ceiling Reflection", "dB": 83.3615}, {"Freq": 143.555, "Measurements": "Ceiling Reflection", "dB": 83.4425}, {"Freq": 148.682, "Measurements": "Ceiling Reflection", "dB": 83.5078}, {"Freq": 153.809, "Measurements": "Ceiling Reflection", "dB": 83.5856}, {"Freq": 159.668, "Measurements": "Ceiling Reflection", "dB": 83.7338}, {"Freq": 164.795, "Measurements": "Ceiling Reflection", "dB": 83.8636}, {"Freq": 170.654, "Measurements": "Ceiling Reflection", "dB": 83.9084}, {"Freq": 176.514, "Measurements": "Ceiling Reflection", "dB": 83.852}, {"Freq": 183.105, "Measurements": "Ceiling Reflection", "dB": 83.7256}, {"Freq": 189.697, "Measurements": "Ceiling Reflection", "dB": 83.8454}, {"Freq": 196.289, "Measurements": "Ceiling Reflection", "dB": 83.8455}, {"Freq": 202.881, "Measurements": "Ceiling Reflection", "dB": 83.8475}, {"Freq": 210.205, "Measurements": "Ceiling Reflection", "dB": 83.7078}, {"Freq": 217.529, "Measurements": "Ceiling Reflection", "dB": 83.6784}, {"Freq": 225.586, "Measurements": "Ceiling Reflection", "dB": 83.4682}, {"Freq": 232.91, "Measurements": "Ceiling Reflection", "dB": 83.5027}, {"Freq": 241.699, "Measurements": "Ceiling Reflection", "dB": 83.5379}, {"Freq": 249.756, "Measurements": "Ceiling Reflection", "dB": 83.5601}, {"Freq": 258.545, "Measurements": "Ceiling Reflection", "dB": 83.4989}, {"Freq": 268.066, "Measurements": "Ceiling Reflection", "dB": 83.2146}, {"Freq": 277.588, "Measurements": "Ceiling Reflection", "dB": 82.9587}, {"Freq": 287.109, "Measurements": "Ceiling Reflection", "dB": 83.2573}, {"Freq": 297.363, "Measurements": "Ceiling Reflection", "dB": 83.0309}, {"Freq": 307.617, "Measurements": "Ceiling Reflection", "dB": 82.8874}, {"Freq": 318.604, "Measurements": "Ceiling Reflection", "dB": 82.764}, {"Freq": 329.59, "Measurements": "Ceiling Reflection", "dB": 82.6367}, {"Freq": 341.309, "Measurements": "Ceiling Reflection", "dB": 82.2448}, {"Freq": 353.76, "Measurements": "Ceiling Reflection", "dB": 82.3684}, {"Freq": 366.211, "Measurements": "Ceiling Reflection", "dB": 82.3522}, {"Freq": 378.662, "Measurements": "Ceiling Reflection", "dB": 82.3176}, {"Freq": 392.578, "Measurements": "Ceiling Reflection", "dB": 81.6443}, {"Freq": 405.762, "Measurements": "Ceiling Reflection", "dB": 82.1791}, {"Freq": 420.41, "Measurements": "Ceiling Reflection", "dB": 82.6591}, {"Freq": 435.059, "Measurements": "Ceiling Reflection", "dB": 82.293}, {"Freq": 450.439, "Measurements": "Ceiling Reflection", "dB": 82.3844}, {"Freq": 466.553, "Measurements": "Ceiling Reflection", "dB": 82.0746}, {"Freq": 482.666, "Measurements": "Ceiling Reflection", "dB": 81.7944}, {"Freq": 500.244, "Measurements": "Ceiling Reflection", "dB": 82.232}, {"Freq": 517.822, "Measurements": "Ceiling Reflection", "dB": 81.8896}, {"Freq": 536.133, "Measurements": "Ceiling Reflection", "dB": 80.9117}, {"Freq": 554.443, "Measurements": "Ceiling Reflection", "dB": 81.4111}, {"Freq": 574.219, "Measurements": "Ceiling Reflection", "dB": 81.5633}, {"Freq": 594.727, "Measurements": "Ceiling Reflection", "dB": 80.3253}, {"Freq": 615.234, "Measurements": "Ceiling Reflection", "dB": 80.5499}, {"Freq": 637.207, "Measurements": "Ceiling Reflection", "dB": 80.6939}, {"Freq": 659.912, "Measurements": "Ceiling Reflection", "dB": 80.8707}, {"Freq": 683.35, "Measurements": "Ceiling Reflection", "dB": 81.2205}, {"Freq": 706.787, "Measurements": "Ceiling Reflection", "dB": 81.1251}, {"Freq": 731.689, "Measurements": "Ceiling Reflection", "dB": 81.4905}, {"Freq": 758.057, "Measurements": "Ceiling Reflection", "dB": 81.946}, {"Freq": 784.424, "Measurements": "Ceiling Reflection", "dB": 82.2049}, {"Freq": 812.256, "Measurements": "Ceiling Reflection", "dB": 82.1775}, {"Freq": 840.82, "Measurements": "Ceiling Reflection", "dB": 82.2452}, {"Freq": 870.85, "Measurements": "Ceiling Reflection", "dB": 81.878}, {"Freq": 901.611, "Measurements": "Ceiling Reflection", "dB": 81.825}, {"Freq": 933.105, "Measurements": "Ceiling Reflection", "dB": 81.6211}, {"Freq": 966.064, "Measurements": "Ceiling Reflection", "dB": 81.7001}, {"Freq": 999.756, "Measurements": "Ceiling Reflection", "dB": 83.4577}, {"Freq": 1034.91, "Measurements": "Ceiling Reflection", "dB": 84.0584}, {"Freq": 1071.53, "Measurements": "Ceiling Reflection", "dB": 84.633}, {"Freq": 1109.62, "Measurements": "Ceiling Reflection", "dB": 84.3802}, {"Freq": 1148.44, "Measurements": "Ceiling Reflection", "dB": 83.7932}, {"Freq": 1189.45, "Measurements": "Ceiling Reflection", "dB": 83.0076}, {"Freq": 1231.2, "Measurements": "Ceiling Reflection", "dB": 83.0419}, {"Freq": 1274.41, "Measurements": "Ceiling Reflection", "dB": 82.8828}, {"Freq": 1319.82, "Measurements": "Ceiling Reflection", "dB": 82.3567}, {"Freq": 1365.97, "Measurements": "Ceiling Reflection", "dB": 82.7314}, {"Freq": 1414.31, "Measurements": "Ceiling Reflection", "dB": 83.3711}, {"Freq": 1464.11, "Measurements": "Ceiling Reflection", "dB": 83.5405}, {"Freq": 1515.38, "Measurements": "Ceiling Reflection", "dB": 82.5099}, {"Freq": 1568.85, "Measurements": "Ceiling Reflection", "dB": 79.6847}, {"Freq": 1624.51, "Measurements": "Ceiling Reflection", "dB": 83.5606}, {"Freq": 1681.64, "Measurements": "Ceiling Reflection", "dB": 84.1127}, {"Freq": 1740.97, "Measurements": "Ceiling Reflection", "dB": 84.105}, {"Freq": 1802.49, "Measurements": "Ceiling Reflection", "dB": 83.6344}, {"Freq": 1866.21, "Measurements": "Ceiling Reflection", "dB": 82.4118}, {"Freq": 1932.13, "Measurements": "Ceiling Reflection", "dB": 81.7057}, {"Freq": 2000.24, "Measurements": "Ceiling Reflection", "dB": 80.4898}, {"Freq": 2070.56, "Measurements": "Ceiling Reflection", "dB": 78.3755}, {"Freq": 2143.8, "Measurements": "Ceiling Reflection", "dB": 77.2728}, {"Freq": 2219.24, "Measurements": "Ceiling Reflection", "dB": 77.1774}, {"Freq": 2297.61, "Measurements": "Ceiling Reflection", "dB": 77.3158}, {"Freq": 2378.17, "Measurements": "Ceiling Reflection", "dB": 75.0907}, {"Freq": 2462.4, "Measurements": "Ceiling Reflection", "dB": 73.7649}, {"Freq": 2548.83, "Measurements": "Ceiling Reflection", "dB": 72.5165}, {"Freq": 2638.92, "Measurements": "Ceiling Reflection", "dB": 75.1067}, {"Freq": 2731.93, "Measurements": "Ceiling Reflection", "dB": 75.5615}, {"Freq": 2828.61, "Measurements": "Ceiling Reflection", "dB": 77.1443}, {"Freq": 2928.22, "Measurements": "Ceiling Reflection", "dB": 77.4505}, {"Freq": 3031.49, "Measurements": "Ceiling Reflection", "dB": 79.3658}, {"Freq": 3138.43, "Measurements": "Ceiling Reflection", "dB": 79.7249}, {"Freq": 3249.02, "Measurements": "Ceiling Reflection", "dB": 80.4605}, {"Freq": 3363.28, "Measurements": "Ceiling Reflection", "dB": 80.9936}, {"Freq": 3481.93, "Measurements": "Ceiling Reflection", "dB": 80.9699}, {"Freq": 3604.98, "Measurements": "Ceiling Reflection", "dB": 81.5526}, {"Freq": 3732.42, "Measurements": "Ceiling Reflection", "dB": 81.4148}, {"Freq": 3863.53, "Measurements": "Ceiling Reflection", "dB": 81.4607}, {"Freq": 3999.76, "Measurements": "Ceiling Reflection", "dB": 81.2994}, {"Freq": 4141.11, "Measurements": "Ceiling Reflection", "dB": 80.923}, {"Freq": 4286.87, "Measurements": "Ceiling Reflection", "dB": 80.4554}, {"Freq": 4438.48, "Measurements": "Ceiling Reflection", "dB": 79.8195}, {"Freq": 4594.48, "Measurements": "Ceiling Reflection", "dB": 79.2086}, {"Freq": 4757.08, "Measurements": "Ceiling Reflection", "dB": 78.8559}, {"Freq": 4924.8, "Measurements": "Ceiling Reflection", "dB": 78.4912}, {"Freq": 5098.39, "Measurements": "Ceiling Reflection", "dB": 78.229}, {"Freq": 5277.83, "Measurements": "Ceiling Reflection", "dB": 77.6432}, {"Freq": 5463.87, "Measurements": "Ceiling Reflection", "dB": 77.374}, {"Freq": 5656.49, "Measurements": "Ceiling Reflection", "dB": 77.2579}, {"Freq": 5856.45, "Measurements": "Ceiling Reflection", "dB": 78.4283}, {"Freq": 6062.99, "Measurements": "Ceiling Reflection", "dB": 79.3438}, {"Freq": 6276.86, "Measurements": "Ceiling Reflection", "dB": 79.541}, {"Freq": 6498.05, "Measurements": "Ceiling Reflection", "dB": 78.6727}, {"Freq": 6727.29, "Measurements": "Ceiling Reflection", "dB": 77.5796}, {"Freq": 6964.6, "Measurements": "Ceiling Reflection", "dB": 76.8314}, {"Freq": 7209.96, "Measurements": "Ceiling Reflection", "dB": 76.4651}, {"Freq": 7464.11, "Measurements": "Ceiling Reflection", "dB": 76.1871}, {"Freq": 7727.78, "Measurements": "Ceiling Reflection", "dB": 76.0907}, {"Freq": 8000.24, "Measurements": "Ceiling Reflection", "dB": 76.4244}, {"Freq": 8282.23, "Measurements": "Ceiling Reflection", "dB": 77.0353}, {"Freq": 8574.46, "Measurements": "Ceiling Reflection", "dB": 77.3519}, {"Freq": 8876.22, "Measurements": "Ceiling Reflection", "dB": 77.4161}, {"Freq": 9189.7, "Measurements": "Ceiling Reflection", "dB": 77.3491}, {"Freq": 9513.43, "Measurements": "Ceiling Reflection", "dB": 77.7072}, {"Freq": 9848.88, "Measurements": "Ceiling Reflection", "dB": 77.9487}, {"Freq": 10196.8, "Measurements": "Ceiling Reflection", "dB": 77.8161}, {"Freq": 10556.4, "Measurements": "Ceiling Reflection", "dB": 76.9975}, {"Freq": 10928.5, "Measurements": "Ceiling Reflection", "dB": 76.0232}, {"Freq": 11313.7, "Measurements": "Ceiling Reflection", "dB": 75.3621}, {"Freq": 11712.9, "Measurements": "Ceiling Reflection", "dB": 75.1259}, {"Freq": 12126.0, "Measurements": "Ceiling Reflection", "dB": 74.9747}, {"Freq": 12553.7, "Measurements": "Ceiling Reflection", "dB": 75.1995}, {"Freq": 12996.1, "Measurements": "Ceiling Reflection", "dB": 75.0916}, {"Freq": 13454.6, "Measurements": "Ceiling Reflection", "dB": 74.5258}, {"Freq": 13928.5, "Measurements": "Ceiling Reflection", "dB": 73.8891}, {"Freq": 14419.9, "Measurements": "Ceiling Reflection", "dB": 73.1684}, {"Freq": 14928.2, "Measurements": "Ceiling Reflection", "dB": 72.5992}, {"Freq": 15454.8, "Measurements": "Ceiling Reflection", "dB": 71.8438}, {"Freq": 15999.8, "Measurements": "Ceiling Reflection", "dB": 70.5464}, {"Freq": 16564.5, "Measurements": "Ceiling Reflection", "dB": 68.1982}, {"Freq": 17148.2, "Measurements": "Ceiling Reflection", "dB": 66.0294}, {"Freq": 17753.2, "Measurements": "Ceiling Reflection", "dB": 64.5548}, {"Freq": 18379.4, "Measurements": "Ceiling Reflection", "dB": 61.5454}, {"Freq": 19027.6, "Measurements": "Ceiling Reflection", "dB": 58.2152}, {"Freq": 19698.5, "Measurements": "Ceiling Reflection", "dB": 61.4147}, {"Freq": 19999.5, "Measurements": "Ceiling Reflection", "dB": 61.5368}, {"Freq": 20.5078, "Measurements": "Total Vertical Reflection", "dB": 41.0866}, {"Freq": 21.2402, "Measurements": "Total Vertical Reflection", "dB": 42.5453}, {"Freq": 21.9727, "Measurements": "Total Vertical Reflection", "dB": 43.826}, {"Freq": 22.7051, "Measurements": "Total Vertical Reflection", "dB": 43.6413}, {"Freq": 23.4375, "Measurements": "Total Vertical Reflection", "dB": 45.5454}, {"Freq": 24.1699, "Measurements": "Total Vertical Reflection", "dB": 45.9463}, {"Freq": 25.6348, "Measurements": "Total Vertical Reflection", "dB": 47.5078}, {"Freq": 26.3672, "Measurements": "Total Vertical Reflection", "dB": 48.3172}, {"Freq": 27.0996, "Measurements": "Total Vertical Reflection", "dB": 49.288}, {"Freq": 27.832, "Measurements": "Total Vertical Reflection", "dB": 50.2819}, {"Freq": 29.2969, "Measurements": "Total Vertical Reflection", "dB": 51.9792}, {"Freq": 30.0293, "Measurements": "Total Vertical Reflection", "dB": 52.3046}, {"Freq": 31.4941, "Measurements": "Total Vertical Reflection", "dB": 54.0519}, {"Freq": 32.2266, "Measurements": "Total Vertical Reflection", "dB": 54.669}, {"Freq": 33.6914, "Measurements": "Total Vertical Reflection", "dB": 56.0912}, {"Freq": 34.4238, "Measurements": "Total Vertical Reflection", "dB": 56.4678}, {"Freq": 35.8887, "Measurements": "Total Vertical Reflection", "dB": 57.9167}, {"Freq": 37.3535, "Measurements": "Total Vertical Reflection", "dB": 59.5452}, {"Freq": 38.8184, "Measurements": "Total Vertical Reflection", "dB": 61.0224}, {"Freq": 39.5508, "Measurements": "Total Vertical Reflection", "dB": 61.7044}, {"Freq": 41.0156, "Measurements": "Total Vertical Reflection", "dB": 62.9399}, {"Freq": 42.4805, "Measurements": "Total Vertical Reflection", "dB": 64.2834}, {"Freq": 43.9453, "Measurements": "Total Vertical Reflection", "dB": 65.7602}, {"Freq": 45.4102, "Measurements": "Total Vertical Reflection", "dB": 67.0378}, {"Freq": 47.6074, "Measurements": "Total Vertical Reflection", "dB": 69.0384}, {"Freq": 49.0723, "Measurements": "Total Vertical Reflection", "dB": 70.346}, {"Freq": 50.5371, "Measurements": "Total Vertical Reflection", "dB": 71.6191}, {"Freq": 52.7344, "Measurements": "Total Vertical Reflection", "dB": 73.564}, {"Freq": 54.1992, "Measurements": "Total Vertical Reflection", "dB": 74.8582}, {"Freq": 56.3965, "Measurements": "Total Vertical Reflection", "dB": 76.7}, {"Freq": 58.5938, "Measurements": "Total Vertical Reflection", "dB": 78.3507}, {"Freq": 60.0586, "Measurements": "Total Vertical Reflection", "dB": 79.4102}, {"Freq": 62.2559, "Measurements": "Total Vertical Reflection", "dB": 80.8642}, {"Freq": 64.4531, "Measurements": "Total Vertical Reflection", "dB": 82.0665}, {"Freq": 66.6504, "Measurements": "Total Vertical Reflection", "dB": 83.0273}, {"Freq": 69.5801, "Measurements": "Total Vertical Reflection", "dB": 83.8478}, {"Freq": 71.7773, "Measurements": "Total Vertical Reflection", "dB": 84.171}, {"Freq": 73.9746, "Measurements": "Total Vertical Reflection", "dB": 84.2736}, {"Freq": 76.9043, "Measurements": "Total Vertical Reflection", "dB": 84.2102}, {"Freq": 79.834, "Measurements": "Total Vertical Reflection", "dB": 84.0203}, {"Freq": 82.7637, "Measurements": "Total Vertical Reflection", "dB": 83.8443}, {"Freq": 85.6934, "Measurements": "Total Vertical Reflection", "dB": 83.6583}, {"Freq": 88.623, "Measurements": "Total Vertical Reflection", "dB": 83.4807}, {"Freq": 91.5527, "Measurements": "Total Vertical Reflection", "dB": 83.2344}, {"Freq": 94.4824, "Measurements": "Total Vertical Reflection", "dB": 83.058}, {"Freq": 98.1445, "Measurements": "Total Vertical Reflection", "dB": 83.0795}, {"Freq": 101.807, "Measurements": "Total Vertical Reflection", "dB": 83.0198}, {"Freq": 105.469, "Measurements": "Total Vertical Reflection", "dB": 82.9683}, {"Freq": 109.131, "Measurements": "Total Vertical Reflection", "dB": 83.0338}, {"Freq": 112.793, "Measurements": "Total Vertical Reflection", "dB": 83.1135}, {"Freq": 116.455, "Measurements": "Total Vertical Reflection", "dB": 83.1153}, {"Freq": 120.85, "Measurements": "Total Vertical Reflection", "dB": 83.2345}, {"Freq": 125.244, "Measurements": "Total Vertical Reflection", "dB": 83.3803}, {"Freq": 129.639, "Measurements": "Total Vertical Reflection", "dB": 83.3968}, {"Freq": 134.033, "Measurements": "Total Vertical Reflection", "dB": 83.3829}, {"Freq": 138.428, "Measurements": "Total Vertical Reflection", "dB": 83.5141}, {"Freq": 143.555, "Measurements": "Total Vertical Reflection", "dB": 83.6274}, {"Freq": 148.682, "Measurements": "Total Vertical Reflection", "dB": 83.7322}, {"Freq": 153.809, "Measurements": "Total Vertical Reflection", "dB": 83.8036}, {"Freq": 159.668, "Measurements": "Total Vertical Reflection", "dB": 83.9672}, {"Freq": 164.795, "Measurements": "Total Vertical Reflection", "dB": 84.1059}, {"Freq": 170.654, "Measurements": "Total Vertical Reflection", "dB": 84.1515}, {"Freq": 176.514, "Measurements": "Total Vertical Reflection", "dB": 84.1152}, {"Freq": 183.105, "Measurements": "Total Vertical Reflection", "dB": 84.0514}, {"Freq": 189.697, "Measurements": "Total Vertical Reflection", "dB": 84.1181}, {"Freq": 196.289, "Measurements": "Total Vertical Reflection", "dB": 84.1336}, {"Freq": 202.881, "Measurements": "Total Vertical Reflection", "dB": 84.1641}, {"Freq": 210.205, "Measurements": "Total Vertical Reflection", "dB": 84.0844}, {"Freq": 217.529, "Measurements": "Total Vertical Reflection", "dB": 84.068}, {"Freq": 225.586, "Measurements": "Total Vertical Reflection", "dB": 83.972}, {"Freq": 232.91, "Measurements": "Total Vertical Reflection", "dB": 84.0733}, {"Freq": 241.699, "Measurements": "Total Vertical Reflection", "dB": 83.9863}, {"Freq": 249.756, "Measurements": "Total Vertical Reflection", "dB": 84.096}, {"Freq": 258.545, "Measurements": "Total Vertical Reflection", "dB": 83.9741}, {"Freq": 268.066, "Measurements": "Total Vertical Reflection", "dB": 83.7388}, {"Freq": 277.588, "Measurements": "Total Vertical Reflection", "dB": 83.6275}, {"Freq": 287.109, "Measurements": "Total Vertical Reflection", "dB": 83.6562}, {"Freq": 297.363, "Measurements": "Total Vertical Reflection", "dB": 83.4817}, {"Freq": 307.617, "Measurements": "Total Vertical Reflection", "dB": 83.4019}, {"Freq": 318.604, "Measurements": "Total Vertical Reflection", "dB": 83.2808}, {"Freq": 329.59, "Measurements": "Total Vertical Reflection", "dB": 83.3442}, {"Freq": 341.309, "Measurements": "Total Vertical Reflection", "dB": 83.128}, {"Freq": 353.76, "Measurements": "Total Vertical Reflection", "dB": 83.5048}, {"Freq": 366.211, "Measurements": "Total Vertical Reflection", "dB": 83.4376}, {"Freq": 378.662, "Measurements": "Total Vertical Reflection", "dB": 83.5283}, {"Freq": 392.578, "Measurements": "Total Vertical Reflection", "dB": 83.0255}, {"Freq": 405.762, "Measurements": "Total Vertical Reflection", "dB": 83.2523}, {"Freq": 420.41, "Measurements": "Total Vertical Reflection", "dB": 83.5764}, {"Freq": 435.059, "Measurements": "Total Vertical Reflection", "dB": 83.1144}, {"Freq": 450.439, "Measurements": "Total Vertical Reflection", "dB": 83.1861}, {"Freq": 466.553, "Measurements": "Total Vertical Reflection", "dB": 82.8303}, {"Freq": 482.666, "Measurements": "Total Vertical Reflection", "dB": 82.6545}, {"Freq": 500.244, "Measurements": "Total Vertical Reflection", "dB": 83.1637}, {"Freq": 517.822, "Measurements": "Total Vertical Reflection", "dB": 82.731}, {"Freq": 536.133, "Measurements": "Total Vertical Reflection", "dB": 82.6616}, {"Freq": 554.443, "Measurements": "Total Vertical Reflection", "dB": 83.2745}, {"Freq": 574.219, "Measurements": "Total Vertical Reflection", "dB": 82.909}, {"Freq": 594.727, "Measurements": "Total Vertical Reflection", "dB": 81.8903}, {"Freq": 615.234, "Measurements": "Total Vertical Reflection", "dB": 82.3614}, {"Freq": 637.207, "Measurements": "Total Vertical Reflection", "dB": 82.5452}, {"Freq": 659.912, "Measurements": "Total Vertical Reflection", "dB": 82.4524}, {"Freq": 683.35, "Measurements": "Total Vertical Reflection", "dB": 82.8441}, {"Freq": 706.787, "Measurements": "Total Vertical Reflection", "dB": 82.9413}, {"Freq": 731.689, "Measurements": "Total Vertical Reflection", "dB": 83.0976}, {"Freq": 758.057, "Measurements": "Total Vertical Reflection", "dB": 83.5863}, {"Freq": 784.424, "Measurements": "Total Vertical Reflection", "dB": 83.5105}, {"Freq": 812.256, "Measurements": "Total Vertical Reflection", "dB": 83.5017}, {"Freq": 840.82, "Measurements": "Total Vertical Reflection", "dB": 83.4191}, {"Freq": 870.85, "Measurements": "Total Vertical Reflection", "dB": 82.9878}, {"Freq": 901.611, "Measurements": "Total Vertical Reflection", "dB": 83.1074}, {"Freq": 933.105, "Measurements": "Total Vertical Reflection", "dB": 83.004}, {"Freq": 966.064, "Measurements": "Total Vertical Reflection", "dB": 83.0595}, {"Freq": 999.756, "Measurements": "Total Vertical Reflection", "dB": 83.643}, {"Freq": 1034.91, "Measurements": "Total Vertical Reflection", "dB": 84.1466}, {"Freq": 1071.53, "Measurements": "Total Vertical Reflection", "dB": 84.5725}, {"Freq": 1109.62, "Measurements": "Total Vertical Reflection", "dB": 84.6521}, {"Freq": 1148.44, "Measurements": "Total Vertical Reflection", "dB": 84.385}, {"Freq": 1189.45, "Measurements": "Total Vertical Reflection", "dB": 83.714}, {"Freq": 1231.2, "Measurements": "Total Vertical Reflection", "dB": 83.8113}, {"Freq": 1274.41, "Measurements": "Total Vertical Reflection", "dB": 83.6425}, {"Freq": 1319.82, "Measurements": "Total Vertical Reflection", "dB": 83.5216}, {"Freq": 1365.97, "Measurements": "Total Vertical Reflection", "dB": 83.4898}, {"Freq": 1414.31, "Measurements": "Total Vertical Reflection", "dB": 83.9345}, {"Freq": 1464.11, "Measurements": "Total Vertical Reflection", "dB": 84.2242}, {"Freq": 1515.38, "Measurements": "Total Vertical Reflection", "dB": 84.4202}, {"Freq": 1568.85, "Measurements": "Total Vertical Reflection", "dB": 82.9473}, {"Freq": 1624.51, "Measurements": "Total Vertical Reflection", "dB": 84.62}, {"Freq": 1681.64, "Measurements": "Total Vertical Reflection", "dB": 84.9187}, {"Freq": 1740.97, "Measurements": "Total Vertical Reflection", "dB": 84.4481}, {"Freq": 1802.49, "Measurements": "Total Vertical Reflection", "dB": 84.1997}, {"Freq": 1866.21, "Measurements": "Total Vertical Reflection", "dB": 83.2781}, {"Freq": 1932.13, "Measurements": "Total Vertical Reflection", "dB": 82.7592}, {"Freq": 2000.24, "Measurements": "Total Vertical Reflection", "dB": 82.095}, {"Freq": 2070.56, "Measurements": "Total Vertical Reflection", "dB": 80.6683}, {"Freq": 2143.8, "Measurements": "Total Vertical Reflection", "dB": 79.6877}, {"Freq": 2219.24, "Measurements": "Total Vertical Reflection", "dB": 78.5502}, {"Freq": 2297.61, "Measurements": "Total Vertical Reflection", "dB": 78.4863}, {"Freq": 2378.17, "Measurements": "Total Vertical Reflection", "dB": 77.5491}, {"Freq": 2462.4, "Measurements": "Total Vertical Reflection", "dB": 76.6144}, {"Freq": 2548.83, "Measurements": "Total Vertical Reflection", "dB": 76.1712}, {"Freq": 2638.92, "Measurements": "Total Vertical Reflection", "dB": 77.1669}, {"Freq": 2731.93, "Measurements": "Total Vertical Reflection", "dB": 76.8597}, {"Freq": 2828.61, "Measurements": "Total Vertical Reflection", "dB": 77.677}, {"Freq": 2928.22, "Measurements": "Total Vertical Reflection", "dB": 77.7201}, {"Freq": 3031.49, "Measurements": "Total Vertical Reflection", "dB": 78.445}, {"Freq": 3138.43, "Measurements": "Total Vertical Reflection", "dB": 79.1136}, {"Freq": 3249.02, "Measurements": "Total Vertical Reflection", "dB": 79.9534}, {"Freq": 3363.28, "Measurements": "Total Vertical Reflection", "dB": 80.2531}, {"Freq": 3481.93, "Measurements": "Total Vertical Reflection", "dB": 80.3774}, {"Freq": 3604.98, "Measurements": "Total Vertical Reflection", "dB": 80.8081}, {"Freq": 3732.42, "Measurements": "Total Vertical Reflection", "dB": 80.8117}, {"Freq": 3863.53, "Measurements": "Total Vertical Reflection", "dB": 80.8059}, {"Freq": 3999.76, "Measurements": "Total Vertical Reflection", "dB": 80.5548}, {"Freq": 4141.11, "Measurements": "Total Vertical Reflection", "dB": 80.0833}, {"Freq": 4286.87, "Measurements": "Total Vertical Reflection", "dB": 79.6866}, {"Freq": 4438.48, "Measurements": "Total Vertical Reflection", "dB": 79.5566}, {"Freq": 4594.48, "Measurements": "Total Vertical Reflection", "dB": 79.4149}, {"Freq": 4757.08, "Measurements": "Total Vertical Reflection", "dB": 79.5185}, {"Freq": 4924.8, "Measurements": "Total Vertical Reflection", "dB": 79.6425}, {"Freq": 5098.39, "Measurements": "Total Vertical Reflection", "dB": 79.7319}, {"Freq": 5277.83, "Measurements": "Total Vertical Reflection", "dB": 79.9434}, {"Freq": 5463.87, "Measurements": "Total Vertical Reflection", "dB": 79.7776}, {"Freq": 5656.49, "Measurements": "Total Vertical Reflection", "dB": 80.0675}, {"Freq": 5856.45, "Measurements": "Total Vertical Reflection", "dB": 80.4375}, {"Freq": 6062.99, "Measurements": "Total Vertical Reflection", "dB": 80.8639}, {"Freq": 6276.86, "Measurements": "Total Vertical Reflection", "dB": 80.7796}, {"Freq": 6498.05, "Measurements": "Total Vertical Reflection", "dB": 80.1437}, {"Freq": 6727.29, "Measurements": "Total Vertical Reflection", "dB": 79.5326}, {"Freq": 6964.6, "Measurements": "Total Vertical Reflection", "dB": 79.0315}, {"Freq": 7209.96, "Measurements": "Total Vertical Reflection", "dB": 78.9919}, {"Freq": 7464.11, "Measurements": "Total Vertical Reflection", "dB": 78.7578}, {"Freq": 7727.78, "Measurements": "Total Vertical Reflection", "dB": 78.3713}, {"Freq": 8000.24, "Measurements": "Total Vertical Reflection", "dB": 78.0787}, {"Freq": 8282.23, "Measurements": "Total Vertical Reflection", "dB": 78.062}, {"Freq": 8574.46, "Measurements": "Total Vertical Reflection", "dB": 78.4281}, {"Freq": 8876.22, "Measurements": "Total Vertical Reflection", "dB": 78.8754}, {"Freq": 9189.7, "Measurements": "Total Vertical Reflection", "dB": 79.2521}, {"Freq": 9513.43, "Measurements": "Total Vertical Reflection", "dB": 79.3428}, {"Freq": 9848.88, "Measurements": "Total Vertical Reflection", "dB": 79.4014}, {"Freq": 10196.8, "Measurements": "Total Vertical Reflection", "dB": 79.1721}, {"Freq": 10556.4, "Measurements": "Total Vertical Reflection", "dB": 78.9409}, {"Freq": 10928.5, "Measurements": "Total Vertical Reflection", "dB": 78.8419}, {"Freq": 11313.7, "Measurements": "Total Vertical Reflection", "dB": 78.6024}, {"Freq": 11712.9, "Measurements": "Total Vertical Reflection", "dB": 78.1016}, {"Freq": 12126.0, "Measurements": "Total Vertical Reflection", "dB": 77.5499}, {"Freq": 12553.7, "Measurements": "Total Vertical Reflection", "dB": 77.5828}, {"Freq": 12996.1, "Measurements": "Total Vertical Reflection", "dB": 77.716}, {"Freq": 13454.6, "Measurements": "Total Vertical Reflection", "dB": 77.5343}, {"Freq": 13928.5, "Measurements": "Total Vertical Reflection", "dB": 77.6227}, {"Freq": 14419.9, "Measurements": "Total Vertical Reflection", "dB": 77.357}, {"Freq": 14928.2, "Measurements": "Total Vertical Reflection", "dB": 77.3509}, {"Freq": 15454.8, "Measurements": "Total Vertical Reflection", "dB": 77.0506}, {"Freq": 15999.8, "Measurements": "Total Vertical Reflection", "dB": 76.2144}, {"Freq": 16564.5, "Measurements": "Total Vertical Reflection", "dB": 74.8204}, {"Freq": 17148.2, "Measurements": "Total Vertical Reflection", "dB": 73.7069}, {"Freq": 17753.2, "Measurements": "Total Vertical Reflection", "dB": 73.0447}, {"Freq": 18379.4, "Measurements": "Total Vertical Reflection", "dB": 71.6618}, {"Freq": 19027.6, "Measurements": "Total Vertical Reflection", "dB": 69.6185}, {"Freq": 19698.5, "Measurements": "Total Vertical Reflection", "dB": 68.7764}, {"Freq": 19999.5, "Measurements": "Total Vertical Reflection", "dB": 68.9784}]}}